{ "results": [
{
	"iicsr": 0.3529085798872441,
	"extractor": "pitch_contour_segmentation",
	"aggregator": "octave_abstraction",
	"distance": "lcs_circular_max"
},
{
	"iicsr": 1.1924534467897372,
	"extractor": "pitch_contour_segmentation",
	"aggregator": "octave_abstraction",
	"distance": "lcs_circular_min"
},
{
	"iicsr": 0.48007664600858696,
	"extractor": "pitch_contour_segmentation",
	"aggregator": "octave_abstraction",
	"distance": "lcs_circular_mean"
},
{
	"iicsr": 0.4485827674601485,
	"extractor": "pitch_contour_segmentation",
	"aggregator": "octave_abstraction",
	"distance": "levenshtein_circular_max"
},
{
	"iicsr": 0.939436947212712,
	"extractor": "pitch_contour_segmentation",
	"aggregator": "octave_abstraction",
	"distance": "levenshtein_circular_min"
},
{
	"iicsr": 0.4538752697569518,
	"extractor": "pitch_contour_segmentation",
	"aggregator": "octave_abstraction",
	"distance": "levenshtein_circular_mean"
},
{
	"iicsr": 0.0341848744452103,
	"extractor": "pitch_contour_segmentation",
	"aggregator": "interval_abstraction",
	"distance": "lcs_max"
},
{
	"iicsr": 0.13510965401378008,
	"extractor": "pitch_contour_segmentation",
	"aggregator": "interval_abstraction",
	"distance": "lcs_min"
},
{
	"iicsr": 0.050519286271408295,
	"extractor": "pitch_contour_segmentation",
	"aggregator": "interval_abstraction",
	"distance": "lcs_mean"
},
{
	"iicsr": 0.06061611543993242,
	"extractor": "pitch_contour_segmentation",
	"aggregator": "interval_abstraction",
	"distance": "levenshtein_max"
},
{
	"iicsr": 0.9364876524115511,
	"extractor": "pitch_contour_segmentation",
	"aggregator": "interval_abstraction",
	"distance": "levenshtein_min"
},
{
	"iicsr": 0.3133149325386181,
	"extractor": "pitch_contour_segmentation",
	"aggregator": "interval_abstraction",
	"distance": "levenshtein_mean"
},
{
	"iicsr": 0.33727835215043306,
	"extractor": "pitch_contour_segmentation",
	"aggregator": "pitch_contour_3_levels",
	"distance": "lcs_max"
},
{
	"iicsr": 1.1781140850122636,
	"extractor": "pitch_contour_segmentation",
	"aggregator": "pitch_contour_3_levels",
	"distance": "lcs_min"
},
{
	"iicsr": 0.4599324385462523,
	"extractor": "pitch_contour_segmentation",
	"aggregator": "pitch_contour_3_levels",
	"distance": "lcs_mean"
},
{
	"iicsr": 0.3857863354450295,
	"extractor": "pitch_contour_segmentation",
	"aggregator": "pitch_contour_3_levels",
	"distance": "levenshtein_max"
},
{
	"iicsr": 0.9434198244613096,
	"extractor": "pitch_contour_segmentation",
	"aggregator": "pitch_contour_3_levels",
	"distance": "levenshtein_min"
},
{
	"iicsr": 0.4347741533850818,
	"extractor": "pitch_contour_segmentation",
	"aggregator": "pitch_contour_3_levels",
	"distance": "levenshtein_mean"
},
{
	"iicsr": 0.3627876222181972,
	"extractor": "pitch_contour_segmentation",
	"aggregator": "pitch_contour_5_levels",
	"distance": "lcs_max"
},
{
	"iicsr": 1.2900674683979199,
	"extractor": "pitch_contour_segmentation",
	"aggregator": "pitch_contour_5_levels",
	"distance": "lcs_min"
},
{
	"iicsr": 0.49253900022360575,
	"extractor": "pitch_contour_segmentation",
	"aggregator": "pitch_contour_5_levels",
	"distance": "lcs_mean"
},
{
	"iicsr": 0.4233150260648694,
	"extractor": "pitch_contour_segmentation",
	"aggregator": "pitch_contour_5_levels",
	"distance": "levenshtein_max"
},
{
	"iicsr": 0.9486845089670904,
	"extractor": "pitch_contour_segmentation",
	"aggregator": "pitch_contour_5_levels",
	"distance": "levenshtein_min"
},
{
	"iicsr": 0.4483319554119343,
	"extractor": "pitch_contour_segmentation",
	"aggregator": "pitch_contour_5_levels",
	"distance": "levenshtein_mean"
},
{
	"iicsr": 0.9452435979881931,
	"extractor": "pitch_contour_segmentation",
	"aggregator": "markov_chain",
	"distance": "circular_euclidean"
},
{
	"iicsr": 1.0095929701809083,
	"extractor": "pitch_contour_segmentation",
	"aggregator": "markov_chain",
	"distance": "circular_manhattan"
},
{
	"iicsr": 0.9452435979881927,
	"extractor": "pitch_contour_segmentation",
	"aggregator": "markov_chain",
	"distance": "circular_chebyshev"
},
{
	"iicsr": 0.6322035942343998,
	"extractor": "pitch_contour_segmentation",
	"aggregator": "markov_chain",
	"distance": "circular_cosine"
},
{
	"iicsr": 0.9637139431716303,
	"extractor": "rhythm_pattern",
	"aggregator": "bypass",
	"distance": "manhattan_distance"
},
{
	"iicsr": 0.962935144080065,
	"extractor": "rhythm_pattern",
	"aggregator": "bypass",
	"distance": "euclidean_distance"
},
{
	"iicsr": 0.9947239953343538,
	"extractor": "rhythm_pattern",
	"aggregator": "bypass",
	"distance": "chebyshev_distance"
},
{
	"iicsr": 1.0168188852851914,
	"extractor": "rhythm_pattern",
	"aggregator": "bypass",
	"distance": "cosine_distance"
},
{
	"iicsr": 0.9267239869429291,
	"extractor": "rhythm_histogram",
	"aggregator": "bypass",
	"distance": "manhattan_distance"
},
{
	"iicsr": 0.9117839166519607,
	"extractor": "rhythm_histogram",
	"aggregator": "bypass",
	"distance": "euclidean_distance"
},
{
	"iicsr": 0.9145866600954182,
	"extractor": "rhythm_histogram",
	"aggregator": "bypass",
	"distance": "chebyshev_distance"
},
{
	"iicsr": 0.7149078192569694,
	"extractor": "rhythm_histogram",
	"aggregator": "bypass",
	"distance": "cosine_distance"
},
{
	"iicsr": 0.9472050202087147,
	"extractor": "temporal_rhythm_histogram",
	"aggregator": "bypass",
	"distance": "manhattan_distance"
},
{
	"iicsr": 0.9972169909808115,
	"extractor": "temporal_rhythm_histogram",
	"aggregator": "bypass",
	"distance": "euclidean_distance"
},
{
	"iicsr": 1.0138174881505668,
	"extractor": "temporal_rhythm_histogram",
	"aggregator": "bypass",
	"distance": "chebyshev_distance"
},
{
	"iicsr": 0.6136947574822991,
	"extractor": "temporal_rhythm_histogram",
	"aggregator": "bypass",
	"distance": "cosine_distance"
},
{
	"iicsr": 0.931319100883941,
	"extractor": "statistical_spectrum_descriptor",
	"aggregator": "bypass",
	"distance": "manhattan_distance"
},
{
	"iicsr": 0.8857331437376387,
	"extractor": "statistical_spectrum_descriptor",
	"aggregator": "bypass",
	"distance": "euclidean_distance"
},
{
	"iicsr": 0.8633083025919859,
	"extractor": "statistical_spectrum_descriptor",
	"aggregator": "bypass",
	"distance": "chebyshev_distance"
},
{
	"iicsr": 0.18109325837747262,
	"extractor": "statistical_spectrum_descriptor",
	"aggregator": "bypass",
	"distance": "cosine_distance"
},
{
	"iicsr": 0.992442718939503,
	"extractor": "temporal_statistical_spectrum_descriptor",
	"aggregator": "bypass",
	"distance": "manhattan_distance"
},
{
	"iicsr": 0.9738035664127567,
	"extractor": "temporal_statistical_spectrum_descriptor",
	"aggregator": "bypass",
	"distance": "euclidean_distance"
},
{
	"iicsr": 0.9505989128027096,
	"extractor": "temporal_statistical_spectrum_descriptor",
	"aggregator": "bypass",
	"distance": "chebyshev_distance"
},
{
	"iicsr": 0.012139746886798797,
	"extractor": "temporal_statistical_spectrum_descriptor",
	"aggregator": "bypass",
	"distance": "cosine_distance"
},
{
	"iicsr": 1.0316285131057328,
	"extractor": "modulation_variance_descriptor",
	"aggregator": "bypass",
	"distance": "manhattan_distance"
},
{
	"iicsr": 1.046766776005638,
	"extractor": "modulation_variance_descriptor",
	"aggregator": "bypass",
	"distance": "euclidean_distance"
},
{
	"iicsr": 0.9506818811554147,
	"extractor": "modulation_variance_descriptor",
	"aggregator": "bypass",
	"distance": "chebyshev_distance"
},
{
	"iicsr": 0.9496741668618267,
	"extractor": "modulation_variance_descriptor",
	"aggregator": "bypass",
	"distance": "cosine_distance"
},
{
	"iicsr": 0.8711778874345965,
	"extractor": "spectral_centroid",
	"aggregator": "basic_stats_1",
	"distance": "manhattan_distance"
},
{
	"iicsr": 0.8901946354692506,
	"extractor": "spectral_centroid",
	"aggregator": "basic_stats_1",
	"distance": "euclidean_distance"
},
{
	"iicsr": 0.95705057118471,
	"extractor": "spectral_centroid",
	"aggregator": "basic_stats_1",
	"distance": "chebyshev_distance"
},
{
	"iicsr": 0.9889054709860231,
	"extractor": "spectral_centroid",
	"aggregator": "basic_stats_1",
	"distance": "cosine_distance"
},
{
	"iicsr": 0.9362845690617084,
	"extractor": "spectral_centroid",
	"aggregator": "basic_stats_2",
	"distance": "manhattan_distance"
},
{
	"iicsr": 0.9556839600377749,
	"extractor": "spectral_centroid",
	"aggregator": "basic_stats_2",
	"distance": "euclidean_distance"
},
{
	"iicsr": 0.9586419436145688,
	"extractor": "spectral_centroid",
	"aggregator": "basic_stats_2",
	"distance": "chebyshev_distance"
},
{
	"iicsr": 1.030595263440053,
	"extractor": "spectral_centroid",
	"aggregator": "basic_stats_2",
	"distance": "cosine_distance"
},
{
	"iicsr": 0.8913344204026757,
	"extractor": "spectral_centroid",
	"aggregator": "diff_stats_1",
	"distance": "manhattan_distance"
},
{
	"iicsr": 0.8924976501836906,
	"extractor": "spectral_centroid",
	"aggregator": "diff_stats_1",
	"distance": "euclidean_distance"
},
{
	"iicsr": 0.9571076134735372,
	"extractor": "spectral_centroid",
	"aggregator": "diff_stats_1",
	"distance": "chebyshev_distance"
},
{
	"iicsr": 0.986719237128086,
	"extractor": "spectral_centroid",
	"aggregator": "diff_stats_1",
	"distance": "cosine_distance"
},
{
	"iicsr": 0.968940646939322,
	"extractor": "spectral_centroid",
	"aggregator": "diff_stats_2",
	"distance": "manhattan_distance"
},
{
	"iicsr": 0.9771269454392131,
	"extractor": "spectral_centroid",
	"aggregator": "diff_stats_2",
	"distance": "euclidean_distance"
},
{
	"iicsr": 0.9858444594331,
	"extractor": "spectral_centroid",
	"aggregator": "diff_stats_2",
	"distance": "chebyshev_distance"
},
{
	"iicsr": 1.0644352180930743,
	"extractor": "spectral_centroid",
	"aggregator": "diff_stats_2",
	"distance": "cosine_distance"
},
{
	"iicsr": 1.0078220261932078,
	"extractor": "spectral_centroid",
	"aggregator": "gaussian_mixture_model_default",
	"distance": "manhattan_distance"
},
{
	"iicsr": 1.0147376381762938,
	"extractor": "spectral_centroid",
	"aggregator": "gaussian_mixture_model_default",
	"distance": "euclidean_distance"
},
{
	"iicsr": 1.0253685955382585,
	"extractor": "spectral_centroid",
	"aggregator": "gaussian_mixture_model_default",
	"distance": "chebyshev_distance"
},
{
	"iicsr": 1.0683162908126815,
	"extractor": "spectral_centroid",
	"aggregator": "gaussian_mixture_model_default",
	"distance": "cosine_distance"
},
{
	"iicsr": 0.5926884174207638,
	"extractor": "spectral_centroid",
	"aggregator": "vector_quantization",
	"distance": "manhattan_distance"
},
{
	"iicsr": 0.8819852719660504,
	"extractor": "spectral_centroid",
	"aggregator": "vector_quantization",
	"distance": "euclidean_distance"
},
{
	"iicsr": 0.8452805536080901,
	"extractor": "spectral_centroid",
	"aggregator": "vector_quantization",
	"distance": "chebyshev_distance"
},
{
	"iicsr": 0.2028532585847764,
	"extractor": "spectral_centroid",
	"aggregator": "vector_quantization",
	"distance": "cosine_distance"
},
{
	"iicsr": 0.807896123924671,
	"extractor": "spectral_centroid",
	"aggregator": "vector_quantization_default",
	"distance": "manhattan_distance"
},
{
	"iicsr": 0.8993888894676487,
	"extractor": "spectral_centroid",
	"aggregator": "vector_quantization_default",
	"distance": "euclidean_distance"
},
{
	"iicsr": 0.8667682717643407,
	"extractor": "spectral_centroid",
	"aggregator": "vector_quantization_default",
	"distance": "chebyshev_distance"
},
{
	"iicsr": 0.8196917692901419,
	"extractor": "spectral_centroid",
	"aggregator": "vector_quantization_default",
	"distance": "cosine_distance"
},
{
	"iicsr": 0.6035990572554251,
	"extractor": "spectral_bandwidth",
	"aggregator": "basic_stats_1",
	"distance": "manhattan_distance"
},
{
	"iicsr": 0.6281781247679794,
	"extractor": "spectral_bandwidth",
	"aggregator": "basic_stats_1",
	"distance": "euclidean_distance"
},
{
	"iicsr": 0.7385483031844324,
	"extractor": "spectral_bandwidth",
	"aggregator": "basic_stats_1",
	"distance": "chebyshev_distance"
},
{
	"iicsr": 0.9724659074760094,
	"extractor": "spectral_bandwidth",
	"aggregator": "basic_stats_1",
	"distance": "cosine_distance"
},
{
	"iicsr": 0.6409783937827149,
	"extractor": "spectral_bandwidth",
	"aggregator": "basic_stats_2",
	"distance": "manhattan_distance"
},
{
	"iicsr": 0.6935883452583858,
	"extractor": "spectral_bandwidth",
	"aggregator": "basic_stats_2",
	"distance": "euclidean_distance"
},
{
	"iicsr": 0.7718609566681451,
	"extractor": "spectral_bandwidth",
	"aggregator": "basic_stats_2",
	"distance": "chebyshev_distance"
},
{
	"iicsr": 0.9919689391540238,
	"extractor": "spectral_bandwidth",
	"aggregator": "basic_stats_2",
	"distance": "cosine_distance"
},
{
	"iicsr": 0.6177727276725936,
	"extractor": "spectral_bandwidth",
	"aggregator": "diff_stats_1",
	"distance": "manhattan_distance"
},
{
	"iicsr": 0.6304047029109181,
	"extractor": "spectral_bandwidth",
	"aggregator": "diff_stats_1",
	"distance": "euclidean_distance"
},
{
	"iicsr": 0.7386887586256263,
	"extractor": "spectral_bandwidth",
	"aggregator": "diff_stats_1",
	"distance": "chebyshev_distance"
},
{
	"iicsr": 0.9732749812821406,
	"extractor": "spectral_bandwidth",
	"aggregator": "diff_stats_1",
	"distance": "cosine_distance"
},
{
	"iicsr": 0.6202864838679548,
	"extractor": "spectral_bandwidth",
	"aggregator": "diff_stats_2",
	"distance": "manhattan_distance"
},
{
	"iicsr": 0.6598581873747756,
	"extractor": "spectral_bandwidth",
	"aggregator": "diff_stats_2",
	"distance": "euclidean_distance"
},
{
	"iicsr": 0.6535689867833606,
	"extractor": "spectral_bandwidth",
	"aggregator": "diff_stats_2",
	"distance": "chebyshev_distance"
},
{
	"iicsr": 0.8845162672719807,
	"extractor": "spectral_bandwidth",
	"aggregator": "diff_stats_2",
	"distance": "cosine_distance"
},
{
	"iicsr": 0.9727154417190599,
	"extractor": "spectral_bandwidth",
	"aggregator": "gaussian_mixture_model_default",
	"distance": "manhattan_distance"
},
{
	"iicsr": 0.9791668653412496,
	"extractor": "spectral_bandwidth",
	"aggregator": "gaussian_mixture_model_default",
	"distance": "euclidean_distance"
},
{
	"iicsr": 0.9775871930861311,
	"extractor": "spectral_bandwidth",
	"aggregator": "gaussian_mixture_model_default",
	"distance": "chebyshev_distance"
},
{
	"iicsr": 1.0147190225060387,
	"extractor": "spectral_bandwidth",
	"aggregator": "gaussian_mixture_model_default",
	"distance": "cosine_distance"
},
{
	"iicsr": 0.057274928206809496,
	"extractor": "spectral_bandwidth",
	"aggregator": "vector_quantization",
	"distance": "manhattan_distance"
},
{
	"iicsr": 0.8479978219343058,
	"extractor": "spectral_bandwidth",
	"aggregator": "vector_quantization",
	"distance": "euclidean_distance"
},
{
	"iicsr": 0.8495701189189877,
	"extractor": "spectral_bandwidth",
	"aggregator": "vector_quantization",
	"distance": "chebyshev_distance"
},
{
	"iicsr": 0.00875656271998141,
	"extractor": "spectral_bandwidth",
	"aggregator": "vector_quantization",
	"distance": "cosine_distance"
},
{
	"iicsr": 0.062270103961003055,
	"extractor": "spectral_bandwidth",
	"aggregator": "vector_quantization_default",
	"distance": "manhattan_distance"
},
{
	"iicsr": 0.5219158388711217,
	"extractor": "spectral_bandwidth",
	"aggregator": "vector_quantization_default",
	"distance": "euclidean_distance"
},
{
	"iicsr": 0.7537161386050611,
	"extractor": "spectral_bandwidth",
	"aggregator": "vector_quantization_default",
	"distance": "chebyshev_distance"
},
{
	"iicsr": 0.052841212576089466,
	"extractor": "spectral_bandwidth",
	"aggregator": "vector_quantization_default",
	"distance": "cosine_distance"
},
{
	"iicsr": 0.7653829744672693,
	"extractor": "spectral_rolloff",
	"aggregator": "basic_stats_1",
	"distance": "manhattan_distance"
},
{
	"iicsr": 0.7933153664801389,
	"extractor": "spectral_rolloff",
	"aggregator": "basic_stats_1",
	"distance": "euclidean_distance"
},
{
	"iicsr": 0.8890997480986278,
	"extractor": "spectral_rolloff",
	"aggregator": "basic_stats_1",
	"distance": "chebyshev_distance"
},
{
	"iicsr": 0.9438330958226938,
	"extractor": "spectral_rolloff",
	"aggregator": "basic_stats_1",
	"distance": "cosine_distance"
},
{
	"iicsr": 0.6642703441299231,
	"extractor": "spectral_rolloff",
	"aggregator": "basic_stats_2",
	"distance": "manhattan_distance"
},
{
	"iicsr": 0.6723425917982685,
	"extractor": "spectral_rolloff",
	"aggregator": "basic_stats_2",
	"distance": "euclidean_distance"
},
{
	"iicsr": 0.6793853254355658,
	"extractor": "spectral_rolloff",
	"aggregator": "basic_stats_2",
	"distance": "chebyshev_distance"
},
{
	"iicsr": 0.9727501518449199,
	"extractor": "spectral_rolloff",
	"aggregator": "basic_stats_2",
	"distance": "cosine_distance"
},
{
	"iicsr": 0.785907060075979,
	"extractor": "spectral_rolloff",
	"aggregator": "diff_stats_1",
	"distance": "manhattan_distance"
},
{
	"iicsr": 0.7956204769377575,
	"extractor": "spectral_rolloff",
	"aggregator": "diff_stats_1",
	"distance": "euclidean_distance"
},
{
	"iicsr": 0.8891522544829592,
	"extractor": "spectral_rolloff",
	"aggregator": "diff_stats_1",
	"distance": "chebyshev_distance"
},
{
	"iicsr": 0.9474484857661144,
	"extractor": "spectral_rolloff",
	"aggregator": "diff_stats_1",
	"distance": "cosine_distance"
},
{
	"iicsr": 0.7245213710142905,
	"extractor": "spectral_rolloff",
	"aggregator": "diff_stats_2",
	"distance": "manhattan_distance"
},
{
	"iicsr": 0.7424977349860921,
	"extractor": "spectral_rolloff",
	"aggregator": "diff_stats_2",
	"distance": "euclidean_distance"
},
{
	"iicsr": 0.7689700029702032,
	"extractor": "spectral_rolloff",
	"aggregator": "diff_stats_2",
	"distance": "chebyshev_distance"
},
{
	"iicsr": 0.960598668518441,
	"extractor": "spectral_rolloff",
	"aggregator": "diff_stats_2",
	"distance": "cosine_distance"
},
{
	"iicsr": 0.9874864755944488,
	"extractor": "spectral_rolloff",
	"aggregator": "gaussian_mixture_model_default",
	"distance": "manhattan_distance"
},
{
	"iicsr": 1.0010362382355984,
	"extractor": "spectral_rolloff",
	"aggregator": "gaussian_mixture_model_default",
	"distance": "euclidean_distance"
},
{
	"iicsr": 1.0031575383501483,
	"extractor": "spectral_rolloff",
	"aggregator": "gaussian_mixture_model_default",
	"distance": "chebyshev_distance"
},
{
	"iicsr": 0.7631642424993782,
	"extractor": "spectral_rolloff",
	"aggregator": "gaussian_mixture_model_default",
	"distance": "cosine_distance"
},
{
	"iicsr": 0.5075531926269394,
	"extractor": "spectral_rolloff",
	"aggregator": "vector_quantization",
	"distance": "manhattan_distance"
},
{
	"iicsr": 0.9061581393249207,
	"extractor": "spectral_rolloff",
	"aggregator": "vector_quantization",
	"distance": "euclidean_distance"
},
{
	"iicsr": 0.8549674776759295,
	"extractor": "spectral_rolloff",
	"aggregator": "vector_quantization",
	"distance": "chebyshev_distance"
},
{
	"iicsr": 0.27468967159410673,
	"extractor": "spectral_rolloff",
	"aggregator": "vector_quantization",
	"distance": "cosine_distance"
},
{
	"iicsr": 0.5374562954048832,
	"extractor": "spectral_rolloff",
	"aggregator": "vector_quantization_default",
	"distance": "manhattan_distance"
},
{
	"iicsr": 0.731939525936603,
	"extractor": "spectral_rolloff",
	"aggregator": "vector_quantization_default",
	"distance": "euclidean_distance"
},
{
	"iicsr": 0.7993331922682065,
	"extractor": "spectral_rolloff",
	"aggregator": "vector_quantization_default",
	"distance": "chebyshev_distance"
},
{
	"iicsr": 0.5522542259229449,
	"extractor": "spectral_rolloff",
	"aggregator": "vector_quantization_default",
	"distance": "cosine_distance"
},
{
	"iicsr": 1.0268015512130488,
	"extractor": "spectral_flatness",
	"aggregator": "basic_stats_1",
	"distance": "manhattan_distance"
},
{
	"iicsr": 1.034460856222474,
	"extractor": "spectral_flatness",
	"aggregator": "basic_stats_1",
	"distance": "euclidean_distance"
},
{
	"iicsr": 1.036515308374546,
	"extractor": "spectral_flatness",
	"aggregator": "basic_stats_1",
	"distance": "chebyshev_distance"
},
{
	"iicsr": 0.7688683312142963,
	"extractor": "spectral_flatness",
	"aggregator": "basic_stats_1",
	"distance": "cosine_distance"
},
{
	"iicsr": 1.1594234008579867,
	"extractor": "spectral_flatness",
	"aggregator": "basic_stats_2",
	"distance": "manhattan_distance"
},
{
	"iicsr": 1.1759649110640438,
	"extractor": "spectral_flatness",
	"aggregator": "basic_stats_2",
	"distance": "euclidean_distance"
},
{
	"iicsr": 1.17722276801359,
	"extractor": "spectral_flatness",
	"aggregator": "basic_stats_2",
	"distance": "chebyshev_distance"
},
{
	"iicsr": 0.8617321652321488,
	"extractor": "spectral_flatness",
	"aggregator": "basic_stats_2",
	"distance": "cosine_distance"
},
{
	"iicsr": 1.0306997398045779,
	"extractor": "spectral_flatness",
	"aggregator": "diff_stats_1",
	"distance": "manhattan_distance"
},
{
	"iicsr": 1.0354641934686226,
	"extractor": "spectral_flatness",
	"aggregator": "diff_stats_1",
	"distance": "euclidean_distance"
},
{
	"iicsr": 1.036602916009925,
	"extractor": "spectral_flatness",
	"aggregator": "diff_stats_1",
	"distance": "chebyshev_distance"
},
{
	"iicsr": 0.6422419415128321,
	"extractor": "spectral_flatness",
	"aggregator": "diff_stats_1",
	"distance": "cosine_distance"
},
{
	"iicsr": 1.1668432244085973,
	"extractor": "spectral_flatness",
	"aggregator": "diff_stats_2",
	"distance": "manhattan_distance"
},
{
	"iicsr": 1.1763784995718178,
	"extractor": "spectral_flatness",
	"aggregator": "diff_stats_2",
	"distance": "euclidean_distance"
},
{
	"iicsr": 1.1774079983075207,
	"extractor": "spectral_flatness",
	"aggregator": "diff_stats_2",
	"distance": "chebyshev_distance"
},
{
	"iicsr": 0.934751566096299,
	"extractor": "spectral_flatness",
	"aggregator": "diff_stats_2",
	"distance": "cosine_distance"
},
{
	"iicsr": 1.1167801760358993,
	"extractor": "spectral_flatness",
	"aggregator": "gaussian_mixture_model_default",
	"distance": "manhattan_distance"
},
{
	"iicsr": 1.231154839119063,
	"extractor": "spectral_flatness",
	"aggregator": "gaussian_mixture_model_default",
	"distance": "euclidean_distance"
},
{
	"iicsr": 1.4774583811970525,
	"extractor": "spectral_flatness",
	"aggregator": "gaussian_mixture_model_default",
	"distance": "chebyshev_distance"
},
{
	"iicsr": 1.395606831592223,
	"extractor": "spectral_flatness",
	"aggregator": "gaussian_mixture_model_default",
	"distance": "cosine_distance"
},
{
	"iicsr": 0.07362717896722865,
	"extractor": "spectral_flatness",
	"aggregator": "vector_quantization",
	"distance": "manhattan_distance"
},
{
	"iicsr": 0.8519603403294524,
	"extractor": "spectral_flatness",
	"aggregator": "vector_quantization",
	"distance": "euclidean_distance"
},
{
	"iicsr": 0.8875605568217119,
	"extractor": "spectral_flatness",
	"aggregator": "vector_quantization",
	"distance": "chebyshev_distance"
},
{
	"iicsr": 0.008120982467180125,
	"extractor": "spectral_flatness",
	"aggregator": "vector_quantization",
	"distance": "cosine_distance"
},
{
	"iicsr": 0.5509402377692196,
	"extractor": "spectral_flatness",
	"aggregator": "vector_quantization_default",
	"distance": "manhattan_distance"
},
{
	"iicsr": 0.5784197475388411,
	"extractor": "spectral_flatness",
	"aggregator": "vector_quantization_default",
	"distance": "euclidean_distance"
},
{
	"iicsr": 0.5478765894568647,
	"extractor": "spectral_flatness",
	"aggregator": "vector_quantization_default",
	"distance": "chebyshev_distance"
},
{
	"iicsr": 0.8244162251416443,
	"extractor": "spectral_flatness",
	"aggregator": "vector_quantization_default",
	"distance": "cosine_distance"
},
{
	"iicsr": 1.0259295348910649,
	"extractor": "rms",
	"aggregator": "basic_stats_1",
	"distance": "manhattan_distance"
},
{
	"iicsr": 1.0259384312098607,
	"extractor": "rms",
	"aggregator": "basic_stats_1",
	"distance": "euclidean_distance"
},
{
	"iicsr": 1.0227408887686344,
	"extractor": "rms",
	"aggregator": "basic_stats_1",
	"distance": "chebyshev_distance"
},
{
	"iicsr": 0.979185293711929,
	"extractor": "rms",
	"aggregator": "basic_stats_1",
	"distance": "cosine_distance"
},
{
	"iicsr": 1.0693586374489878,
	"extractor": "rms",
	"aggregator": "basic_stats_2",
	"distance": "manhattan_distance"
},
{
	"iicsr": 1.089859824199121,
	"extractor": "rms",
	"aggregator": "basic_stats_2",
	"distance": "euclidean_distance"
},
{
	"iicsr": 1.1072254767418572,
	"extractor": "rms",
	"aggregator": "basic_stats_2",
	"distance": "chebyshev_distance"
},
{
	"iicsr": 0.9917960697363852,
	"extractor": "rms",
	"aggregator": "basic_stats_2",
	"distance": "cosine_distance"
},
{
	"iicsr": 1.028279355279397,
	"extractor": "rms",
	"aggregator": "diff_stats_1",
	"distance": "manhattan_distance"
},
{
	"iicsr": 1.0265707862874216,
	"extractor": "rms",
	"aggregator": "diff_stats_1",
	"distance": "euclidean_distance"
},
{
	"iicsr": 1.022750219382875,
	"extractor": "rms",
	"aggregator": "diff_stats_1",
	"distance": "chebyshev_distance"
},
{
	"iicsr": 0.980905832888013,
	"extractor": "rms",
	"aggregator": "diff_stats_1",
	"distance": "cosine_distance"
},
{
	"iicsr": 1.0789300744766381,
	"extractor": "rms",
	"aggregator": "diff_stats_2",
	"distance": "manhattan_distance"
},
{
	"iicsr": 1.0941005194252713,
	"extractor": "rms",
	"aggregator": "diff_stats_2",
	"distance": "euclidean_distance"
},
{
	"iicsr": 1.107969707008084,
	"extractor": "rms",
	"aggregator": "diff_stats_2",
	"distance": "chebyshev_distance"
},
{
	"iicsr": 1.019004972034741,
	"extractor": "rms",
	"aggregator": "diff_stats_2",
	"distance": "cosine_distance"
},
{
	"iicsr": 1.0393298053016282,
	"extractor": "rms",
	"aggregator": "gaussian_mixture_model_default",
	"distance": "manhattan_distance"
},
{
	"iicsr": 1.0997239430503751,
	"extractor": "rms",
	"aggregator": "gaussian_mixture_model_default",
	"distance": "euclidean_distance"
},
{
	"iicsr": 1.2465763690897012,
	"extractor": "rms",
	"aggregator": "gaussian_mixture_model_default",
	"distance": "chebyshev_distance"
},
{
	"iicsr": 1.0321593933613775,
	"extractor": "rms",
	"aggregator": "gaussian_mixture_model_default",
	"distance": "cosine_distance"
},
{
	"iicsr": 0.4812499329153044,
	"extractor": "rms",
	"aggregator": "vector_quantization",
	"distance": "manhattan_distance"
},
{
	"iicsr": 0.9073911435089305,
	"extractor": "rms",
	"aggregator": "vector_quantization",
	"distance": "euclidean_distance"
},
{
	"iicsr": 0.8729763348863743,
	"extractor": "rms",
	"aggregator": "vector_quantization",
	"distance": "chebyshev_distance"
},
{
	"iicsr": 0.07102636655986275,
	"extractor": "rms",
	"aggregator": "vector_quantization",
	"distance": "cosine_distance"
},
{
	"iicsr": 0.5900835058174035,
	"extractor": "rms",
	"aggregator": "vector_quantization_default",
	"distance": "manhattan_distance"
},
{
	"iicsr": 0.7466331398976112,
	"extractor": "rms",
	"aggregator": "vector_quantization_default",
	"distance": "euclidean_distance"
},
{
	"iicsr": 0.8860292330880076,
	"extractor": "rms",
	"aggregator": "vector_quantization_default",
	"distance": "chebyshev_distance"
},
{
	"iicsr": 0.45668351555392006,
	"extractor": "rms",
	"aggregator": "vector_quantization_default",
	"distance": "cosine_distance"
},
{
	"iicsr": 0.9272996198238441,
	"extractor": "zero_crossing_rate",
	"aggregator": "basic_stats_1",
	"distance": "manhattan_distance"
},
{
	"iicsr": 0.9169715096658082,
	"extractor": "zero_crossing_rate",
	"aggregator": "basic_stats_1",
	"distance": "euclidean_distance"
},
{
	"iicsr": 0.8827316232397597,
	"extractor": "zero_crossing_rate",
	"aggregator": "basic_stats_1",
	"distance": "chebyshev_distance"
},
{
	"iicsr": 0.9733317169338503,
	"extractor": "zero_crossing_rate",
	"aggregator": "basic_stats_1",
	"distance": "cosine_distance"
},
{
	"iicsr": 0.6988649538438874,
	"extractor": "zero_crossing_rate",
	"aggregator": "basic_stats_2",
	"distance": "manhattan_distance"
},
{
	"iicsr": 0.6515052345405123,
	"extractor": "zero_crossing_rate",
	"aggregator": "basic_stats_2",
	"distance": "euclidean_distance"
},
{
	"iicsr": 0.6409633746382992,
	"extractor": "zero_crossing_rate",
	"aggregator": "basic_stats_2",
	"distance": "chebyshev_distance"
},
{
	"iicsr": 0.981369266238634,
	"extractor": "zero_crossing_rate",
	"aggregator": "basic_stats_2",
	"distance": "cosine_distance"
},
{
	"iicsr": 0.9427971207459395,
	"extractor": "zero_crossing_rate",
	"aggregator": "diff_stats_1",
	"distance": "manhattan_distance"
},
{
	"iicsr": 0.919046838113233,
	"extractor": "zero_crossing_rate",
	"aggregator": "diff_stats_1",
	"distance": "euclidean_distance"
},
{
	"iicsr": 0.882773183004256,
	"extractor": "zero_crossing_rate",
	"aggregator": "diff_stats_1",
	"distance": "chebyshev_distance"
},
{
	"iicsr": 0.9677731491802573,
	"extractor": "zero_crossing_rate",
	"aggregator": "diff_stats_1",
	"distance": "cosine_distance"
},
{
	"iicsr": 0.7091256959039642,
	"extractor": "zero_crossing_rate",
	"aggregator": "diff_stats_2",
	"distance": "manhattan_distance"
},
{
	"iicsr": 0.6563890875835379,
	"extractor": "zero_crossing_rate",
	"aggregator": "diff_stats_2",
	"distance": "euclidean_distance"
},
{
	"iicsr": 0.641388239049161,
	"extractor": "zero_crossing_rate",
	"aggregator": "diff_stats_2",
	"distance": "chebyshev_distance"
},
{
	"iicsr": 0.9899251928462581,
	"extractor": "zero_crossing_rate",
	"aggregator": "diff_stats_2",
	"distance": "cosine_distance"
},
{
	"iicsr": 0.56108593918878,
	"extractor": "zero_crossing_rate",
	"aggregator": "gaussian_mixture_model_default",
	"distance": "manhattan_distance"
},
{
	"iicsr": 0.5871328906460613,
	"extractor": "zero_crossing_rate",
	"aggregator": "gaussian_mixture_model_default",
	"distance": "euclidean_distance"
},
{
	"iicsr": 0.7932015872516378,
	"extractor": "zero_crossing_rate",
	"aggregator": "gaussian_mixture_model_default",
	"distance": "chebyshev_distance"
},
{
	"iicsr": 0.5334581223004417,
	"extractor": "zero_crossing_rate",
	"aggregator": "gaussian_mixture_model_default",
	"distance": "cosine_distance"
},
{
	"iicsr": 1.0195596662185493,
	"extractor": "zero_crossing_rate",
	"aggregator": "vector_quantization",
	"distance": "manhattan_distance"
},
{
	"iicsr": 0.9002751803630349,
	"extractor": "zero_crossing_rate",
	"aggregator": "vector_quantization",
	"distance": "euclidean_distance"
},
{
	"iicsr": 0.8524595562283116,
	"extractor": "zero_crossing_rate",
	"aggregator": "vector_quantization",
	"distance": "chebyshev_distance"
},
{
	"iicsr": 0.4778694255619284,
	"extractor": "zero_crossing_rate",
	"aggregator": "vector_quantization",
	"distance": "cosine_distance"
},
{
	"iicsr": 1.0735992417598035,
	"extractor": "zero_crossing_rate",
	"aggregator": "vector_quantization_default",
	"distance": "manhattan_distance"
},
{
	"iicsr": 1.0032201878111562,
	"extractor": "zero_crossing_rate",
	"aggregator": "vector_quantization_default",
	"distance": "euclidean_distance"
},
{
	"iicsr": 0.9784499454195722,
	"extractor": "zero_crossing_rate",
	"aggregator": "vector_quantization_default",
	"distance": "chebyshev_distance"
},
{
	"iicsr": 1.0018696400149838,
	"extractor": "zero_crossing_rate",
	"aggregator": "vector_quantization_default",
	"distance": "cosine_distance"
},
{
	"iicsr": 0.9971071688980419,
	"extractor": "chroma_stft",
	"aggregator": "basic_stats_1",
	"distance": "manhattan_distance"
},
{
	"iicsr": 1.0081050041373762,
	"extractor": "chroma_stft",
	"aggregator": "basic_stats_1",
	"distance": "euclidean_distance"
},
{
	"iicsr": 0.9995090932627771,
	"extractor": "chroma_stft",
	"aggregator": "basic_stats_1",
	"distance": "chebyshev_distance"
},
{
	"iicsr": 1.0226865814760178,
	"extractor": "chroma_stft",
	"aggregator": "basic_stats_1",
	"distance": "cosine_distance"
},
{
	"iicsr": 0.9981626004132735,
	"extractor": "chroma_stft",
	"aggregator": "basic_stats_2",
	"distance": "manhattan_distance"
},
{
	"iicsr": 1.0082110071113002,
	"extractor": "chroma_stft",
	"aggregator": "basic_stats_2",
	"distance": "euclidean_distance"
},
{
	"iicsr": 1.001506956833211,
	"extractor": "chroma_stft",
	"aggregator": "basic_stats_2",
	"distance": "chebyshev_distance"
},
{
	"iicsr": 1.0107367976549324,
	"extractor": "chroma_stft",
	"aggregator": "basic_stats_2",
	"distance": "cosine_distance"
},
{
	"iicsr": 0.9104180517188407,
	"extractor": "chroma_stft",
	"aggregator": "diff_stats_1",
	"distance": "manhattan_distance"
},
{
	"iicsr": 0.9618077146203211,
	"extractor": "chroma_stft",
	"aggregator": "diff_stats_1",
	"distance": "euclidean_distance"
},
{
	"iicsr": 1.000058256103337,
	"extractor": "chroma_stft",
	"aggregator": "diff_stats_1",
	"distance": "chebyshev_distance"
},
{
	"iicsr": 0.98336192298466,
	"extractor": "chroma_stft",
	"aggregator": "diff_stats_1",
	"distance": "cosine_distance"
},
{
	"iicsr": 0.9839913171026957,
	"extractor": "chroma_stft",
	"aggregator": "diff_stats_2",
	"distance": "manhattan_distance"
},
{
	"iicsr": 1.0218678923338596,
	"extractor": "chroma_stft",
	"aggregator": "diff_stats_2",
	"distance": "euclidean_distance"
},
{
	"iicsr": 1.079047588971117,
	"extractor": "chroma_stft",
	"aggregator": "diff_stats_2",
	"distance": "chebyshev_distance"
},
{
	"iicsr": 1.0052738534798613,
	"extractor": "chroma_stft",
	"aggregator": "diff_stats_2",
	"distance": "cosine_distance"
},
{
	"iicsr": 0.8942992495796495,
	"extractor": "chroma_stft",
	"aggregator": "statistical_summarization",
	"distance": "manhattan_distance"
},
{
	"iicsr": 0.9482911427754204,
	"extractor": "chroma_stft",
	"aggregator": "statistical_summarization",
	"distance": "euclidean_distance"
},
{
	"iicsr": 0.9978571450690312,
	"extractor": "chroma_stft",
	"aggregator": "statistical_summarization",
	"distance": "chebyshev_distance"
},
{
	"iicsr": 0.9901297023350192,
	"extractor": "chroma_stft",
	"aggregator": "statistical_summarization",
	"distance": "cosine_distance"
},
{
	"iicsr": 1.2487452545016045,
	"extractor": "chroma_stft",
	"aggregator": "gaussian_mixture_model_default",
	"distance": "manhattan_distance"
},
{
	"iicsr": 1.3908687242957154,
	"extractor": "chroma_stft",
	"aggregator": "gaussian_mixture_model_default",
	"distance": "euclidean_distance"
},
{
	"iicsr": 0.7837184172766004,
	"extractor": "chroma_stft",
	"aggregator": "gaussian_mixture_model_default",
	"distance": "chebyshev_distance"
},
{
	"iicsr": 1.3975964512278887,
	"extractor": "chroma_stft",
	"aggregator": "gaussian_mixture_model_default",
	"distance": "cosine_distance"
},
{
	"iicsr": 0.5594547041529849,
	"extractor": "chroma_stft",
	"aggregator": "vector_quantization",
	"distance": "manhattan_distance"
},
{
	"iicsr": 0.8985226359505499,
	"extractor": "chroma_stft",
	"aggregator": "vector_quantization",
	"distance": "euclidean_distance"
},
{
	"iicsr": 0.8964515149034683,
	"extractor": "chroma_stft",
	"aggregator": "vector_quantization",
	"distance": "chebyshev_distance"
},
{
	"iicsr": 0.47132334161636225,
	"extractor": "chroma_stft",
	"aggregator": "vector_quantization",
	"distance": "cosine_distance"
},
{
	"iicsr": 1.0111299284879665,
	"extractor": "chroma_stft",
	"aggregator": "vector_quantization_default",
	"distance": "manhattan_distance"
},
{
	"iicsr": 1.0532985050207206,
	"extractor": "chroma_stft",
	"aggregator": "vector_quantization_default",
	"distance": "euclidean_distance"
},
{
	"iicsr": 1.0348302984853561,
	"extractor": "chroma_stft",
	"aggregator": "vector_quantization_default",
	"distance": "chebyshev_distance"
},
{
	"iicsr": 1.085030874194126,
	"extractor": "chroma_stft",
	"aggregator": "vector_quantization_default",
	"distance": "cosine_distance"
},
{
	"iicsr": 1.0432465770240855,
	"extractor": "chroma_stft",
	"aggregator": "statistical_summarization_2",
	"distance": "earth_movers_distance"
},
{
	"iicsr": 1.0030555883271959,
	"extractor": "chroma_stft",
	"aggregator": "statistical_summarization_2",
	"distance": "monte_carlo_distance"
},
{
	"iicsr": 0.8565539226661479,
	"extractor": "chroma_cqt",
	"aggregator": "basic_stats_1",
	"distance": "manhattan_distance"
},
{
	"iicsr": 0.8049216450485621,
	"extractor": "chroma_cqt",
	"aggregator": "basic_stats_1",
	"distance": "euclidean_distance"
},
{
	"iicsr": 0.7493316897415624,
	"extractor": "chroma_cqt",
	"aggregator": "basic_stats_1",
	"distance": "chebyshev_distance"
},
{
	"iicsr": 0.9279851433857205,
	"extractor": "chroma_cqt",
	"aggregator": "basic_stats_1",
	"distance": "cosine_distance"
},
{
	"iicsr": 0.8513836434621762,
	"extractor": "chroma_cqt",
	"aggregator": "basic_stats_2",
	"distance": "manhattan_distance"
},
{
	"iicsr": 0.8059753482788097,
	"extractor": "chroma_cqt",
	"aggregator": "basic_stats_2",
	"distance": "euclidean_distance"
},
{
	"iicsr": 0.7493991670943098,
	"extractor": "chroma_cqt",
	"aggregator": "basic_stats_2",
	"distance": "chebyshev_distance"
},
{
	"iicsr": 0.8830126087494029,
	"extractor": "chroma_cqt",
	"aggregator": "basic_stats_2",
	"distance": "cosine_distance"
},
{
	"iicsr": 0.8189002144816194,
	"extractor": "chroma_cqt",
	"aggregator": "diff_stats_1",
	"distance": "manhattan_distance"
},
{
	"iicsr": 0.8005174983297076,
	"extractor": "chroma_cqt",
	"aggregator": "diff_stats_1",
	"distance": "euclidean_distance"
},
{
	"iicsr": 0.7493316897415624,
	"extractor": "chroma_cqt",
	"aggregator": "diff_stats_1",
	"distance": "chebyshev_distance"
},
{
	"iicsr": 0.9306636996322525,
	"extractor": "chroma_cqt",
	"aggregator": "diff_stats_1",
	"distance": "cosine_distance"
},
{
	"iicsr": 0.9282898727669947,
	"extractor": "chroma_cqt",
	"aggregator": "diff_stats_2",
	"distance": "manhattan_distance"
},
{
	"iicsr": 0.917757530267159,
	"extractor": "chroma_cqt",
	"aggregator": "diff_stats_2",
	"distance": "euclidean_distance"
},
{
	"iicsr": 1.0420099471311985,
	"extractor": "chroma_cqt",
	"aggregator": "diff_stats_2",
	"distance": "chebyshev_distance"
},
{
	"iicsr": 0.9304870208266831,
	"extractor": "chroma_cqt",
	"aggregator": "diff_stats_2",
	"distance": "cosine_distance"
},
{
	"iicsr": 0.8461728313593673,
	"extractor": "chroma_cqt",
	"aggregator": "statistical_summarization",
	"distance": "manhattan_distance"
},
{
	"iicsr": 0.8018728423209084,
	"extractor": "chroma_cqt",
	"aggregator": "statistical_summarization",
	"distance": "euclidean_distance"
},
{
	"iicsr": 0.746798939954952,
	"extractor": "chroma_cqt",
	"aggregator": "statistical_summarization",
	"distance": "chebyshev_distance"
},
{
	"iicsr": 0.9818612773498911,
	"extractor": "chroma_cqt",
	"aggregator": "statistical_summarization",
	"distance": "cosine_distance"
},
{
	"iicsr": 1.0255605248987465,
	"extractor": "chroma_cqt",
	"aggregator": "gaussian_mixture_model_default",
	"distance": "manhattan_distance"
},
{
	"iicsr": 1.0274883120273433,
	"extractor": "chroma_cqt",
	"aggregator": "gaussian_mixture_model_default",
	"distance": "euclidean_distance"
},
{
	"iicsr": 0.6135725383952605,
	"extractor": "chroma_cqt",
	"aggregator": "gaussian_mixture_model_default",
	"distance": "chebyshev_distance"
},
{
	"iicsr": 1.0868831197276525,
	"extractor": "chroma_cqt",
	"aggregator": "gaussian_mixture_model_default",
	"distance": "cosine_distance"
},
{
	"iicsr": 0.7306565526524585,
	"extractor": "chroma_cqt",
	"aggregator": "vector_quantization",
	"distance": "manhattan_distance"
},
{
	"iicsr": 0.9558003430237375,
	"extractor": "chroma_cqt",
	"aggregator": "vector_quantization",
	"distance": "euclidean_distance"
},
{
	"iicsr": 0.9617415076655355,
	"extractor": "chroma_cqt",
	"aggregator": "vector_quantization",
	"distance": "chebyshev_distance"
},
{
	"iicsr": 0.39840517573555684,
	"extractor": "chroma_cqt",
	"aggregator": "vector_quantization",
	"distance": "cosine_distance"
},
{
	"iicsr": 0.9429081798882379,
	"extractor": "chroma_cqt",
	"aggregator": "vector_quantization_default",
	"distance": "manhattan_distance"
},
{
	"iicsr": 0.9487874952767301,
	"extractor": "chroma_cqt",
	"aggregator": "vector_quantization_default",
	"distance": "euclidean_distance"
},
{
	"iicsr": 0.8804174694222467,
	"extractor": "chroma_cqt",
	"aggregator": "vector_quantization_default",
	"distance": "chebyshev_distance"
},
{
	"iicsr": 0.9809952040081957,
	"extractor": "chroma_cqt",
	"aggregator": "vector_quantization_default",
	"distance": "cosine_distance"
},
{
	"iicsr": 0.8230966048677935,
	"extractor": "chroma_cqt",
	"aggregator": "statistical_summarization_2",
	"distance": "earth_movers_distance"
},
{
	"iicsr": 1.0044742824423214,
	"extractor": "chroma_cqt",
	"aggregator": "statistical_summarization_2",
	"distance": "monte_carlo_distance"
},
{
	"iicsr": 0.813897478715209,
	"extractor": "chroma_cens",
	"aggregator": "basic_stats_1",
	"distance": "manhattan_distance"
},
{
	"iicsr": 0.8594756817203926,
	"extractor": "chroma_cens",
	"aggregator": "basic_stats_1",
	"distance": "euclidean_distance"
},
{
	"iicsr": 1.0099638124359387,
	"extractor": "chroma_cens",
	"aggregator": "basic_stats_1",
	"distance": "chebyshev_distance"
},
{
	"iicsr": 0.9200834664403107,
	"extractor": "chroma_cens",
	"aggregator": "basic_stats_1",
	"distance": "cosine_distance"
},
{
	"iicsr": 0.8475692455087205,
	"extractor": "chroma_cens",
	"aggregator": "basic_stats_2",
	"distance": "manhattan_distance"
},
{
	"iicsr": 0.9186415756291308,
	"extractor": "chroma_cens",
	"aggregator": "basic_stats_2",
	"distance": "euclidean_distance"
},
{
	"iicsr": 0.9588976057309501,
	"extractor": "chroma_cens",
	"aggregator": "basic_stats_2",
	"distance": "chebyshev_distance"
},
{
	"iicsr": 0.9934230211531704,
	"extractor": "chroma_cens",
	"aggregator": "basic_stats_2",
	"distance": "cosine_distance"
},
{
	"iicsr": 0.8186414107692439,
	"extractor": "chroma_cens",
	"aggregator": "diff_stats_1",
	"distance": "manhattan_distance"
},
{
	"iicsr": 0.8598108540932663,
	"extractor": "chroma_cens",
	"aggregator": "diff_stats_1",
	"distance": "euclidean_distance"
},
{
	"iicsr": 1.0099638124359387,
	"extractor": "chroma_cens",
	"aggregator": "diff_stats_1",
	"distance": "chebyshev_distance"
},
{
	"iicsr": 0.9202639185764685,
	"extractor": "chroma_cens",
	"aggregator": "diff_stats_1",
	"distance": "cosine_distance"
},
{
	"iicsr": 0.6671099709771126,
	"extractor": "chroma_cens",
	"aggregator": "diff_stats_2",
	"distance": "manhattan_distance"
},
{
	"iicsr": 0.6049542311639434,
	"extractor": "chroma_cens",
	"aggregator": "diff_stats_2",
	"distance": "euclidean_distance"
},
{
	"iicsr": 0.4415654922306664,
	"extractor": "chroma_cens",
	"aggregator": "diff_stats_2",
	"distance": "chebyshev_distance"
},
{
	"iicsr": 0.7357030550136041,
	"extractor": "chroma_cens",
	"aggregator": "diff_stats_2",
	"distance": "cosine_distance"
},
{
	"iicsr": 0.8351695972689189,
	"extractor": "chroma_cens",
	"aggregator": "statistical_summarization",
	"distance": "manhattan_distance"
},
{
	"iicsr": 0.9010630312529058,
	"extractor": "chroma_cens",
	"aggregator": "statistical_summarization",
	"distance": "euclidean_distance"
},
{
	"iicsr": 1.006859759578917,
	"extractor": "chroma_cens",
	"aggregator": "statistical_summarization",
	"distance": "chebyshev_distance"
},
{
	"iicsr": 0.9747250592476912,
	"extractor": "chroma_cens",
	"aggregator": "statistical_summarization",
	"distance": "cosine_distance"
},
{
	"iicsr": 0.8745715288081883,
	"extractor": "chroma_cens",
	"aggregator": "gaussian_mixture_model_default",
	"distance": "manhattan_distance"
},
{
	"iicsr": 1.0611386692017108,
	"extractor": "chroma_cens",
	"aggregator": "gaussian_mixture_model_default",
	"distance": "euclidean_distance"
},
{
	"iicsr": 1.2280211673845427,
	"extractor": "chroma_cens",
	"aggregator": "gaussian_mixture_model_default",
	"distance": "chebyshev_distance"
},
{
	"iicsr": 1.0636236639394967,
	"extractor": "chroma_cens",
	"aggregator": "gaussian_mixture_model_default",
	"distance": "cosine_distance"
},
{
	"iicsr": 0.4979051101925178,
	"extractor": "chroma_cens",
	"aggregator": "vector_quantization",
	"distance": "manhattan_distance"
},
{
	"iicsr": 0.988842820695905,
	"extractor": "chroma_cens",
	"aggregator": "vector_quantization",
	"distance": "euclidean_distance"
},
{
	"iicsr": 1.0596338605221853,
	"extractor": "chroma_cens",
	"aggregator": "vector_quantization",
	"distance": "chebyshev_distance"
},
{
	"iicsr": 0.559032297917088,
	"extractor": "chroma_cens",
	"aggregator": "vector_quantization",
	"distance": "cosine_distance"
},
{
	"iicsr": 0.9615532499297547,
	"extractor": "chroma_cens",
	"aggregator": "vector_quantization_default",
	"distance": "manhattan_distance"
},
{
	"iicsr": 0.990767128866833,
	"extractor": "chroma_cens",
	"aggregator": "vector_quantization_default",
	"distance": "euclidean_distance"
},
{
	"iicsr": 0.9515788570293806,
	"extractor": "chroma_cens",
	"aggregator": "vector_quantization_default",
	"distance": "chebyshev_distance"
},
{
	"iicsr": 1.092581605422842,
	"extractor": "chroma_cens",
	"aggregator": "vector_quantization_default",
	"distance": "cosine_distance"
},
{
	"iicsr": 0.8473955594091949,
	"extractor": "chroma_cens",
	"aggregator": "statistical_summarization_2",
	"distance": "earth_movers_distance"
},
{
	"iicsr": 1.0239089467747053,
	"extractor": "chroma_cens",
	"aggregator": "statistical_summarization_2",
	"distance": "monte_carlo_distance"
},
{
	"iicsr": 1.0537869534306175,
	"extractor": "beat_synchronous_chroma_stft",
	"aggregator": "basic_stats_1",
	"distance": "manhattan_distance"
},
{
	"iicsr": 1.0576580833146654,
	"extractor": "beat_synchronous_chroma_stft",
	"aggregator": "basic_stats_1",
	"distance": "euclidean_distance"
},
{
	"iicsr": 1.0808326732759657,
	"extractor": "beat_synchronous_chroma_stft",
	"aggregator": "basic_stats_1",
	"distance": "chebyshev_distance"
},
{
	"iicsr": 1.075482005311585,
	"extractor": "beat_synchronous_chroma_stft",
	"aggregator": "basic_stats_1",
	"distance": "cosine_distance"
},
{
	"iicsr": 1.0701212664390702,
	"extractor": "beat_synchronous_chroma_stft",
	"aggregator": "basic_stats_2",
	"distance": "manhattan_distance"
},
{
	"iicsr": 1.0711416246422856,
	"extractor": "beat_synchronous_chroma_stft",
	"aggregator": "basic_stats_2",
	"distance": "euclidean_distance"
},
{
	"iicsr": 1.092939720481327,
	"extractor": "beat_synchronous_chroma_stft",
	"aggregator": "basic_stats_2",
	"distance": "chebyshev_distance"
},
{
	"iicsr": 1.0515854363732322,
	"extractor": "beat_synchronous_chroma_stft",
	"aggregator": "basic_stats_2",
	"distance": "cosine_distance"
},
{
	"iicsr": 1.043247842803192,
	"extractor": "beat_synchronous_chroma_stft",
	"aggregator": "diff_stats_1",
	"distance": "manhattan_distance"
},
{
	"iicsr": 1.0605786785528493,
	"extractor": "beat_synchronous_chroma_stft",
	"aggregator": "diff_stats_1",
	"distance": "euclidean_distance"
},
{
	"iicsr": 1.0868719064400667,
	"extractor": "beat_synchronous_chroma_stft",
	"aggregator": "diff_stats_1",
	"distance": "chebyshev_distance"
},
{
	"iicsr": 1.0528276165452704,
	"extractor": "beat_synchronous_chroma_stft",
	"aggregator": "diff_stats_1",
	"distance": "cosine_distance"
},
{
	"iicsr": 0.9506372648121957,
	"extractor": "beat_synchronous_chroma_stft",
	"aggregator": "diff_stats_2",
	"distance": "manhattan_distance"
},
{
	"iicsr": 0.8961207302789608,
	"extractor": "beat_synchronous_chroma_stft",
	"aggregator": "diff_stats_2",
	"distance": "euclidean_distance"
},
{
	"iicsr": 0.8225278499909833,
	"extractor": "beat_synchronous_chroma_stft",
	"aggregator": "diff_stats_2",
	"distance": "chebyshev_distance"
},
{
	"iicsr": 1.0092543383943682,
	"extractor": "beat_synchronous_chroma_stft",
	"aggregator": "diff_stats_2",
	"distance": "cosine_distance"
},
{
	"iicsr": 0.9934995376022168,
	"extractor": "beat_synchronous_chroma_stft",
	"aggregator": "statistical_summarization",
	"distance": "manhattan_distance"
},
{
	"iicsr": 1.0429888846194986,
	"extractor": "beat_synchronous_chroma_stft",
	"aggregator": "statistical_summarization",
	"distance": "euclidean_distance"
},
{
	"iicsr": 1.1751971916470634,
	"extractor": "beat_synchronous_chroma_stft",
	"aggregator": "statistical_summarization",
	"distance": "chebyshev_distance"
},
{
	"iicsr": 1.0589145268451194,
	"extractor": "beat_synchronous_chroma_stft",
	"aggregator": "statistical_summarization",
	"distance": "cosine_distance"
},
{
	"iicsr": 0.7787983436340867,
	"extractor": "beat_synchronous_chroma_stft",
	"aggregator": "gaussian_mixture_model_default",
	"distance": "manhattan_distance"
},
{
	"iicsr": 0.6891685288263392,
	"extractor": "beat_synchronous_chroma_stft",
	"aggregator": "gaussian_mixture_model_default",
	"distance": "euclidean_distance"
},
{
	"iicsr": 0.38506237941629773,
	"extractor": "beat_synchronous_chroma_stft",
	"aggregator": "gaussian_mixture_model_default",
	"distance": "chebyshev_distance"
},
{
	"iicsr": 0.8207790471150731,
	"extractor": "beat_synchronous_chroma_stft",
	"aggregator": "gaussian_mixture_model_default",
	"distance": "cosine_distance"
},
{
	"iicsr": 0.9770740953049215,
	"extractor": "beat_synchronous_chroma_stft",
	"aggregator": "vector_quantization",
	"distance": "manhattan_distance"
},
{
	"iicsr": 1.0126687826669865,
	"extractor": "beat_synchronous_chroma_stft",
	"aggregator": "vector_quantization",
	"distance": "euclidean_distance"
},
{
	"iicsr": 1.0180921195286166,
	"extractor": "beat_synchronous_chroma_stft",
	"aggregator": "vector_quantization",
	"distance": "chebyshev_distance"
},
{
	"iicsr": 1.002924432529836,
	"extractor": "beat_synchronous_chroma_stft",
	"aggregator": "vector_quantization",
	"distance": "cosine_distance"
},
{
	"iicsr": 1.1306738012897748,
	"extractor": "beat_synchronous_chroma_stft",
	"aggregator": "vector_quantization_default",
	"distance": "manhattan_distance"
},
{
	"iicsr": 1.1449191310890434,
	"extractor": "beat_synchronous_chroma_stft",
	"aggregator": "vector_quantization_default",
	"distance": "euclidean_distance"
},
{
	"iicsr": 1.1939820082935246,
	"extractor": "beat_synchronous_chroma_stft",
	"aggregator": "vector_quantization_default",
	"distance": "chebyshev_distance"
},
{
	"iicsr": 1.2055841638777678,
	"extractor": "beat_synchronous_chroma_stft",
	"aggregator": "vector_quantization_default",
	"distance": "cosine_distance"
},
{
	"iicsr": 0.9889591572003048,
	"extractor": "beat_synchronous_chroma_stft",
	"aggregator": "statistical_summarization_2",
	"distance": "earth_movers_distance"
},
{
	"iicsr": 1.0003042046857504,
	"extractor": "beat_synchronous_chroma_stft",
	"aggregator": "statistical_summarization_2",
	"distance": "monte_carlo_distance"
},
{
	"iicsr": 0.8249861938137404,
	"extractor": "beat_synchronous_chroma_cqt",
	"aggregator": "basic_stats_1",
	"distance": "manhattan_distance"
},
{
	"iicsr": 0.8209810389618489,
	"extractor": "beat_synchronous_chroma_cqt",
	"aggregator": "basic_stats_1",
	"distance": "euclidean_distance"
},
{
	"iicsr": 0.8562032567011082,
	"extractor": "beat_synchronous_chroma_cqt",
	"aggregator": "basic_stats_1",
	"distance": "chebyshev_distance"
},
{
	"iicsr": 0.9446326297318467,
	"extractor": "beat_synchronous_chroma_cqt",
	"aggregator": "basic_stats_1",
	"distance": "cosine_distance"
},
{
	"iicsr": 0.8885083903934762,
	"extractor": "beat_synchronous_chroma_cqt",
	"aggregator": "basic_stats_2",
	"distance": "manhattan_distance"
},
{
	"iicsr": 0.9269798502112521,
	"extractor": "beat_synchronous_chroma_cqt",
	"aggregator": "basic_stats_2",
	"distance": "euclidean_distance"
},
{
	"iicsr": 1.1680379280496398,
	"extractor": "beat_synchronous_chroma_cqt",
	"aggregator": "basic_stats_2",
	"distance": "chebyshev_distance"
},
{
	"iicsr": 0.9815845479192952,
	"extractor": "beat_synchronous_chroma_cqt",
	"aggregator": "basic_stats_2",
	"distance": "cosine_distance"
},
{
	"iicsr": 0.9268407299533261,
	"extractor": "beat_synchronous_chroma_cqt",
	"aggregator": "diff_stats_1",
	"distance": "manhattan_distance"
},
{
	"iicsr": 0.8719425603871307,
	"extractor": "beat_synchronous_chroma_cqt",
	"aggregator": "diff_stats_1",
	"distance": "euclidean_distance"
},
{
	"iicsr": 0.8607950822827327,
	"extractor": "beat_synchronous_chroma_cqt",
	"aggregator": "diff_stats_1",
	"distance": "chebyshev_distance"
},
{
	"iicsr": 0.9648566609483616,
	"extractor": "beat_synchronous_chroma_cqt",
	"aggregator": "diff_stats_1",
	"distance": "cosine_distance"
},
{
	"iicsr": 0.790337925120688,
	"extractor": "beat_synchronous_chroma_cqt",
	"aggregator": "diff_stats_2",
	"distance": "manhattan_distance"
},
{
	"iicsr": 0.770800966125512,
	"extractor": "beat_synchronous_chroma_cqt",
	"aggregator": "diff_stats_2",
	"distance": "euclidean_distance"
},
{
	"iicsr": 0.9380482872115056,
	"extractor": "beat_synchronous_chroma_cqt",
	"aggregator": "diff_stats_2",
	"distance": "chebyshev_distance"
},
{
	"iicsr": 0.8703745488042568,
	"extractor": "beat_synchronous_chroma_cqt",
	"aggregator": "diff_stats_2",
	"distance": "cosine_distance"
},
{
	"iicsr": 0.8680712475305289,
	"extractor": "beat_synchronous_chroma_cqt",
	"aggregator": "statistical_summarization",
	"distance": "manhattan_distance"
},
{
	"iicsr": 0.8229485307032128,
	"extractor": "beat_synchronous_chroma_cqt",
	"aggregator": "statistical_summarization",
	"distance": "euclidean_distance"
},
{
	"iicsr": 0.8513158346825912,
	"extractor": "beat_synchronous_chroma_cqt",
	"aggregator": "statistical_summarization",
	"distance": "chebyshev_distance"
},
{
	"iicsr": 1.0103196211459584,
	"extractor": "beat_synchronous_chroma_cqt",
	"aggregator": "statistical_summarization",
	"distance": "cosine_distance"
},
{
	"iicsr": 1.0393532529685594,
	"extractor": "beat_synchronous_chroma_cqt",
	"aggregator": "gaussian_mixture_model_default",
	"distance": "manhattan_distance"
},
{
	"iicsr": 0.9742012870055011,
	"extractor": "beat_synchronous_chroma_cqt",
	"aggregator": "gaussian_mixture_model_default",
	"distance": "euclidean_distance"
},
{
	"iicsr": 0.7519676247060488,
	"extractor": "beat_synchronous_chroma_cqt",
	"aggregator": "gaussian_mixture_model_default",
	"distance": "chebyshev_distance"
},
{
	"iicsr": 1.0764554793711867,
	"extractor": "beat_synchronous_chroma_cqt",
	"aggregator": "gaussian_mixture_model_default",
	"distance": "cosine_distance"
},
{
	"iicsr": 0.39845766439886526,
	"extractor": "beat_synchronous_chroma_cqt",
	"aggregator": "vector_quantization",
	"distance": "manhattan_distance"
},
{
	"iicsr": 0.9878785731889244,
	"extractor": "beat_synchronous_chroma_cqt",
	"aggregator": "vector_quantization",
	"distance": "euclidean_distance"
},
{
	"iicsr": 1.0353448468254178,
	"extractor": "beat_synchronous_chroma_cqt",
	"aggregator": "vector_quantization",
	"distance": "chebyshev_distance"
},
{
	"iicsr": 0.3685525872257386,
	"extractor": "beat_synchronous_chroma_cqt",
	"aggregator": "vector_quantization",
	"distance": "cosine_distance"
},
{
	"iicsr": 1.0408851994032904,
	"extractor": "beat_synchronous_chroma_cqt",
	"aggregator": "vector_quantization_default",
	"distance": "manhattan_distance"
},
{
	"iicsr": 0.9314226632440405,
	"extractor": "beat_synchronous_chroma_cqt",
	"aggregator": "vector_quantization_default",
	"distance": "euclidean_distance"
},
{
	"iicsr": 0.8491794702754748,
	"extractor": "beat_synchronous_chroma_cqt",
	"aggregator": "vector_quantization_default",
	"distance": "chebyshev_distance"
},
{
	"iicsr": 0.901095939901792,
	"extractor": "beat_synchronous_chroma_cqt",
	"aggregator": "vector_quantization_default",
	"distance": "cosine_distance"
},
{
	"iicsr": 0.7611103384973795,
	"extractor": "beat_synchronous_chroma_cqt",
	"aggregator": "statistical_summarization_2",
	"distance": "earth_movers_distance"
},
{
	"iicsr": 1.0010770271374678,
	"extractor": "beat_synchronous_chroma_cqt",
	"aggregator": "statistical_summarization_2",
	"distance": "monte_carlo_distance"
},
{
	"iicsr": 0.9132877025129801,
	"extractor": "beat_synchronous_chroma_cens",
	"aggregator": "basic_stats_1",
	"distance": "manhattan_distance"
},
{
	"iicsr": 0.9353115700956555,
	"extractor": "beat_synchronous_chroma_cens",
	"aggregator": "basic_stats_1",
	"distance": "euclidean_distance"
},
{
	"iicsr": 1.0124993721219988,
	"extractor": "beat_synchronous_chroma_cens",
	"aggregator": "basic_stats_1",
	"distance": "chebyshev_distance"
},
{
	"iicsr": 0.9766974348250421,
	"extractor": "beat_synchronous_chroma_cens",
	"aggregator": "basic_stats_1",
	"distance": "cosine_distance"
},
{
	"iicsr": 0.9033419216878956,
	"extractor": "beat_synchronous_chroma_cens",
	"aggregator": "basic_stats_2",
	"distance": "manhattan_distance"
},
{
	"iicsr": 0.9533783817847066,
	"extractor": "beat_synchronous_chroma_cens",
	"aggregator": "basic_stats_2",
	"distance": "euclidean_distance"
},
{
	"iicsr": 1.1066569183197472,
	"extractor": "beat_synchronous_chroma_cens",
	"aggregator": "basic_stats_2",
	"distance": "chebyshev_distance"
},
{
	"iicsr": 1.021975789840762,
	"extractor": "beat_synchronous_chroma_cens",
	"aggregator": "basic_stats_2",
	"distance": "cosine_distance"
},
{
	"iicsr": 0.9888008973809006,
	"extractor": "beat_synchronous_chroma_cens",
	"aggregator": "diff_stats_1",
	"distance": "manhattan_distance"
},
{
	"iicsr": 0.9793055491058251,
	"extractor": "beat_synchronous_chroma_cens",
	"aggregator": "diff_stats_1",
	"distance": "euclidean_distance"
},
{
	"iicsr": 1.0168437694889876,
	"extractor": "beat_synchronous_chroma_cens",
	"aggregator": "diff_stats_1",
	"distance": "chebyshev_distance"
},
{
	"iicsr": 0.9957643477747938,
	"extractor": "beat_synchronous_chroma_cens",
	"aggregator": "diff_stats_1",
	"distance": "cosine_distance"
},
{
	"iicsr": 0.81734667119165,
	"extractor": "beat_synchronous_chroma_cens",
	"aggregator": "diff_stats_2",
	"distance": "manhattan_distance"
},
{
	"iicsr": 0.8038375464045557,
	"extractor": "beat_synchronous_chroma_cens",
	"aggregator": "diff_stats_2",
	"distance": "euclidean_distance"
},
{
	"iicsr": 0.9387177122121656,
	"extractor": "beat_synchronous_chroma_cens",
	"aggregator": "diff_stats_2",
	"distance": "chebyshev_distance"
},
{
	"iicsr": 0.9973023502796768,
	"extractor": "beat_synchronous_chroma_cens",
	"aggregator": "diff_stats_2",
	"distance": "cosine_distance"
},
{
	"iicsr": 0.9871477335469242,
	"extractor": "beat_synchronous_chroma_cens",
	"aggregator": "statistical_summarization",
	"distance": "manhattan_distance"
},
{
	"iicsr": 0.9660572782500444,
	"extractor": "beat_synchronous_chroma_cens",
	"aggregator": "statistical_summarization",
	"distance": "euclidean_distance"
},
{
	"iicsr": 1.0073414025290415,
	"extractor": "beat_synchronous_chroma_cens",
	"aggregator": "statistical_summarization",
	"distance": "chebyshev_distance"
},
{
	"iicsr": 1.0159132070562154,
	"extractor": "beat_synchronous_chroma_cens",
	"aggregator": "statistical_summarization",
	"distance": "cosine_distance"
},
{
	"iicsr": 0.7682265418444322,
	"extractor": "beat_synchronous_chroma_cens",
	"aggregator": "gaussian_mixture_model_default",
	"distance": "manhattan_distance"
},
{
	"iicsr": 0.8670139856685481,
	"extractor": "beat_synchronous_chroma_cens",
	"aggregator": "gaussian_mixture_model_default",
	"distance": "euclidean_distance"
},
{
	"iicsr": 1.1655916903459143,
	"extractor": "beat_synchronous_chroma_cens",
	"aggregator": "gaussian_mixture_model_default",
	"distance": "chebyshev_distance"
},
{
	"iicsr": 0.9027275349591694,
	"extractor": "beat_synchronous_chroma_cens",
	"aggregator": "gaussian_mixture_model_default",
	"distance": "cosine_distance"
},
{
	"iicsr": 0.6094209604926076,
	"extractor": "beat_synchronous_chroma_cens",
	"aggregator": "vector_quantization",
	"distance": "manhattan_distance"
},
{
	"iicsr": 1.042241411526823,
	"extractor": "beat_synchronous_chroma_cens",
	"aggregator": "vector_quantization",
	"distance": "euclidean_distance"
},
{
	"iicsr": 1.0475531980387052,
	"extractor": "beat_synchronous_chroma_cens",
	"aggregator": "vector_quantization",
	"distance": "chebyshev_distance"
},
{
	"iicsr": 0.70105208447805,
	"extractor": "beat_synchronous_chroma_cens",
	"aggregator": "vector_quantization",
	"distance": "cosine_distance"
},
{
	"iicsr": 0.9181847459870504,
	"extractor": "beat_synchronous_chroma_cens",
	"aggregator": "vector_quantization_default",
	"distance": "manhattan_distance"
},
{
	"iicsr": 0.9838906670846922,
	"extractor": "beat_synchronous_chroma_cens",
	"aggregator": "vector_quantization_default",
	"distance": "euclidean_distance"
},
{
	"iicsr": 1.0292563958872345,
	"extractor": "beat_synchronous_chroma_cens",
	"aggregator": "vector_quantization_default",
	"distance": "chebyshev_distance"
},
{
	"iicsr": 0.9570230657671763,
	"extractor": "beat_synchronous_chroma_cens",
	"aggregator": "vector_quantization_default",
	"distance": "cosine_distance"
},
{
	"iicsr": 0.882948271121651,
	"extractor": "beat_synchronous_chroma_cens",
	"aggregator": "statistical_summarization_2",
	"distance": "earth_movers_distance"
},
{
	"iicsr": 1.0003708434072776,
	"extractor": "beat_synchronous_chroma_cens",
	"aggregator": "statistical_summarization_2",
	"distance": "monte_carlo_distance"
},
{
	"iicsr": 1.0582786269579887,
	"extractor": "melspectrogram",
	"aggregator": "basic_stats_1",
	"distance": "manhattan_distance"
},
{
	"iicsr": 1.072874628770652,
	"extractor": "melspectrogram",
	"aggregator": "basic_stats_1",
	"distance": "euclidean_distance"
},
{
	"iicsr": 1.076740584268827,
	"extractor": "melspectrogram",
	"aggregator": "basic_stats_1",
	"distance": "chebyshev_distance"
},
{
	"iicsr": 1.366000920680695,
	"extractor": "melspectrogram",
	"aggregator": "basic_stats_1",
	"distance": "cosine_distance"
},
{
	"iicsr": 1.0580481091628346,
	"extractor": "melspectrogram",
	"aggregator": "basic_stats_2",
	"distance": "manhattan_distance"
},
{
	"iicsr": 1.0873359618603888,
	"extractor": "melspectrogram",
	"aggregator": "basic_stats_2",
	"distance": "euclidean_distance"
},
{
	"iicsr": 1.150487877299365,
	"extractor": "melspectrogram",
	"aggregator": "basic_stats_2",
	"distance": "chebyshev_distance"
},
{
	"iicsr": 1.0015484421574814,
	"extractor": "melspectrogram",
	"aggregator": "basic_stats_2",
	"distance": "cosine_distance"
},
{
	"iicsr": 1.0554635765573739,
	"extractor": "melspectrogram",
	"aggregator": "diff_stats_1",
	"distance": "manhattan_distance"
},
{
	"iicsr": 1.0731233713387962,
	"extractor": "melspectrogram",
	"aggregator": "diff_stats_1",
	"distance": "euclidean_distance"
},
{
	"iicsr": 1.076741705817502,
	"extractor": "melspectrogram",
	"aggregator": "diff_stats_1",
	"distance": "chebyshev_distance"
},
{
	"iicsr": 1.3504538081720838,
	"extractor": "melspectrogram",
	"aggregator": "diff_stats_1",
	"distance": "cosine_distance"
},
{
	"iicsr": 1.055040126413743,
	"extractor": "melspectrogram",
	"aggregator": "diff_stats_2",
	"distance": "manhattan_distance"
},
{
	"iicsr": 1.0847662935780706,
	"extractor": "melspectrogram",
	"aggregator": "diff_stats_2",
	"distance": "euclidean_distance"
},
{
	"iicsr": 1.1504881669325753,
	"extractor": "melspectrogram",
	"aggregator": "diff_stats_2",
	"distance": "chebyshev_distance"
},
{
	"iicsr": 1.0101108089718567,
	"extractor": "melspectrogram",
	"aggregator": "diff_stats_2",
	"distance": "cosine_distance"
},
{
	"iicsr": 1.0197546478965418,
	"extractor": "melspectrogram",
	"aggregator": "statistical_summarization",
	"distance": "manhattan_distance"
},
{
	"iicsr": 1.0242221628523747,
	"extractor": "melspectrogram",
	"aggregator": "statistical_summarization",
	"distance": "euclidean_distance"
},
{
	"iicsr": 1.0262193236118557,
	"extractor": "melspectrogram",
	"aggregator": "statistical_summarization",
	"distance": "chebyshev_distance"
},
{
	"iicsr": 1.604631244445697,
	"extractor": "melspectrogram",
	"aggregator": "statistical_summarization",
	"distance": "cosine_distance"
},
{
	"iicsr": 1.0152019175554508,
	"extractor": "melspectrogram",
	"aggregator": "gaussian_mixture_model_default",
	"distance": "manhattan_distance"
},
{
	"iicsr": 1.0265541771465443,
	"extractor": "melspectrogram",
	"aggregator": "gaussian_mixture_model_default",
	"distance": "euclidean_distance"
},
{
	"iicsr": 1.0305701972821875,
	"extractor": "melspectrogram",
	"aggregator": "gaussian_mixture_model_default",
	"distance": "chebyshev_distance"
},
{
	"iicsr": 0.6831515240879826,
	"extractor": "melspectrogram",
	"aggregator": "gaussian_mixture_model_default",
	"distance": "cosine_distance"
},
{
	"iicsr": 0.10914151852014084,
	"extractor": "melspectrogram",
	"aggregator": "vector_quantization",
	"distance": "manhattan_distance"
},
{
	"iicsr": 0.8815129757245151,
	"extractor": "melspectrogram",
	"aggregator": "vector_quantization",
	"distance": "euclidean_distance"
},
{
	"iicsr": 0.9295940395368868,
	"extractor": "melspectrogram",
	"aggregator": "vector_quantization",
	"distance": "chebyshev_distance"
},
{
	"iicsr": 0.018692950771502796,
	"extractor": "melspectrogram",
	"aggregator": "vector_quantization",
	"distance": "cosine_distance"
},
{
	"iicsr": 0.6574807196715149,
	"extractor": "melspectrogram",
	"aggregator": "vector_quantization_default",
	"distance": "manhattan_distance"
},
{
	"iicsr": 0.7435892604157628,
	"extractor": "melspectrogram",
	"aggregator": "vector_quantization_default",
	"distance": "euclidean_distance"
},
{
	"iicsr": 0.6151114060250412,
	"extractor": "melspectrogram",
	"aggregator": "vector_quantization_default",
	"distance": "chebyshev_distance"
},
{
	"iicsr": 0.564565028435949,
	"extractor": "melspectrogram",
	"aggregator": "vector_quantization_default",
	"distance": "cosine_distance"
},
{
	"iicsr": 1.0510688055492567,
	"extractor": "melspectrogram",
	"aggregator": "statistical_summarization_2",
	"distance": "earth_movers_distance"
},
{
	"iicsr": 1.0000541120816149,
	"extractor": "melspectrogram",
	"aggregator": "statistical_summarization_2",
	"distance": "monte_carlo_distance"
},
{
	"iicsr": 0.7082862195437895,
	"extractor": "mfcc",
	"aggregator": "basic_stats_1",
	"distance": "manhattan_distance"
},
{
	"iicsr": 0.6825506230474054,
	"extractor": "mfcc",
	"aggregator": "basic_stats_1",
	"distance": "euclidean_distance"
},
{
	"iicsr": 0.7570615287582247,
	"extractor": "mfcc",
	"aggregator": "basic_stats_1",
	"distance": "chebyshev_distance"
},
{
	"iicsr": 0.8732133592840956,
	"extractor": "mfcc",
	"aggregator": "basic_stats_1",
	"distance": "cosine_distance"
},
{
	"iicsr": 0.6625935754365617,
	"extractor": "mfcc",
	"aggregator": "basic_stats_2",
	"distance": "manhattan_distance"
},
{
	"iicsr": 0.5990002443043808,
	"extractor": "mfcc",
	"aggregator": "basic_stats_2",
	"distance": "euclidean_distance"
},
{
	"iicsr": 0.7025594085268972,
	"extractor": "mfcc",
	"aggregator": "basic_stats_2",
	"distance": "chebyshev_distance"
},
{
	"iicsr": 0.8060464405722577,
	"extractor": "mfcc",
	"aggregator": "basic_stats_2",
	"distance": "cosine_distance"
},
{
	"iicsr": 0.6462745347582811,
	"extractor": "mfcc",
	"aggregator": "diff_stats_1",
	"distance": "manhattan_distance"
},
{
	"iicsr": 0.6698031704464219,
	"extractor": "mfcc",
	"aggregator": "diff_stats_1",
	"distance": "euclidean_distance"
},
{
	"iicsr": 0.7570615287582247,
	"extractor": "mfcc",
	"aggregator": "diff_stats_1",
	"distance": "chebyshev_distance"
},
{
	"iicsr": 0.87395403824109,
	"extractor": "mfcc",
	"aggregator": "diff_stats_1",
	"distance": "cosine_distance"
},
{
	"iicsr": 0.6430807655447445,
	"extractor": "mfcc",
	"aggregator": "diff_stats_2",
	"distance": "manhattan_distance"
},
{
	"iicsr": 0.6442316513829754,
	"extractor": "mfcc",
	"aggregator": "diff_stats_2",
	"distance": "euclidean_distance"
},
{
	"iicsr": 0.7067125653193368,
	"extractor": "mfcc",
	"aggregator": "diff_stats_2",
	"distance": "chebyshev_distance"
},
{
	"iicsr": 0.7563490951606592,
	"extractor": "mfcc",
	"aggregator": "diff_stats_2",
	"distance": "cosine_distance"
},
{
	"iicsr": 0.9113323739225422,
	"extractor": "mfcc",
	"aggregator": "statistical_summarization",
	"distance": "manhattan_distance"
},
{
	"iicsr": 0.7932665375087237,
	"extractor": "mfcc",
	"aggregator": "statistical_summarization",
	"distance": "euclidean_distance"
},
{
	"iicsr": 0.8240403272898976,
	"extractor": "mfcc",
	"aggregator": "statistical_summarization",
	"distance": "chebyshev_distance"
},
{
	"iicsr": 0.7541857930227003,
	"extractor": "mfcc",
	"aggregator": "statistical_summarization",
	"distance": "cosine_distance"
},
{
	"iicsr": 0.8975325825789345,
	"extractor": "mfcc",
	"aggregator": "gaussian_mixture_model_default",
	"distance": "manhattan_distance"
},
{
	"iicsr": 0.886756885336545,
	"extractor": "mfcc",
	"aggregator": "gaussian_mixture_model_default",
	"distance": "euclidean_distance"
},
{
	"iicsr": 0.9421913383598902,
	"extractor": "mfcc",
	"aggregator": "gaussian_mixture_model_default",
	"distance": "chebyshev_distance"
},
{
	"iicsr": 0.6923826767499232,
	"extractor": "mfcc",
	"aggregator": "gaussian_mixture_model_default",
	"distance": "cosine_distance"
},
{
	"iicsr": 1.3312796673968417e-15,
	"extractor": "mfcc",
	"aggregator": "vector_quantization",
	"distance": "manhattan_distance"
},
{
	"iicsr": 0.9221533196871093,
	"extractor": "mfcc",
	"aggregator": "vector_quantization",
	"distance": "euclidean_distance"
},
{
	"iicsr": 0.9326489966416232,
	"extractor": "mfcc",
	"aggregator": "vector_quantization",
	"distance": "chebyshev_distance"
},
{
	"iicsr": 0.0,
	"extractor": "mfcc",
	"aggregator": "vector_quantization",
	"distance": "cosine_distance"
},
{
	"iicsr": 0.36805951511082025,
	"extractor": "mfcc",
	"aggregator": "vector_quantization_default",
	"distance": "manhattan_distance"
},
{
	"iicsr": 0.7000236827252245,
	"extractor": "mfcc",
	"aggregator": "vector_quantization_default",
	"distance": "euclidean_distance"
},
{
	"iicsr": 0.8691242097459763,
	"extractor": "mfcc",
	"aggregator": "vector_quantization_default",
	"distance": "chebyshev_distance"
},
{
	"iicsr": 0.34419713222771703,
	"extractor": "mfcc",
	"aggregator": "vector_quantization_default",
	"distance": "cosine_distance"
},
{
	"iicsr": 0.6156694183797599,
	"extractor": "mfcc",
	"aggregator": "statistical_summarization_2",
	"distance": "earth_movers_distance"
},
{
	"iicsr": 0.969869766761289,
	"extractor": "mfcc",
	"aggregator": "statistical_summarization_2",
	"distance": "monte_carlo_distance"
},
{
	"iicsr": 0.5594616599586687,
	"extractor": "spectral_contrast",
	"aggregator": "basic_stats_1",
	"distance": "manhattan_distance"
},
{
	"iicsr": 0.4510655214451067,
	"extractor": "spectral_contrast",
	"aggregator": "basic_stats_1",
	"distance": "euclidean_distance"
},
{
	"iicsr": 0.432542173185343,
	"extractor": "spectral_contrast",
	"aggregator": "basic_stats_1",
	"distance": "chebyshev_distance"
},
{
	"iicsr": 0.5877430869747292,
	"extractor": "spectral_contrast",
	"aggregator": "basic_stats_1",
	"distance": "cosine_distance"
},
{
	"iicsr": 0.5602448227144879,
	"extractor": "spectral_contrast",
	"aggregator": "basic_stats_2",
	"distance": "manhattan_distance"
},
{
	"iicsr": 0.4196151818373707,
	"extractor": "spectral_contrast",
	"aggregator": "basic_stats_2",
	"distance": "euclidean_distance"
},
{
	"iicsr": 0.4759519236914484,
	"extractor": "spectral_contrast",
	"aggregator": "basic_stats_2",
	"distance": "chebyshev_distance"
},
{
	"iicsr": 0.5217860385475587,
	"extractor": "spectral_contrast",
	"aggregator": "basic_stats_2",
	"distance": "cosine_distance"
},
{
	"iicsr": 0.5477991681541061,
	"extractor": "spectral_contrast",
	"aggregator": "diff_stats_1",
	"distance": "manhattan_distance"
},
{
	"iicsr": 0.4523238739237779,
	"extractor": "spectral_contrast",
	"aggregator": "diff_stats_1",
	"distance": "euclidean_distance"
},
{
	"iicsr": 0.4325437867143305,
	"extractor": "spectral_contrast",
	"aggregator": "diff_stats_1",
	"distance": "chebyshev_distance"
},
{
	"iicsr": 0.5905528912834384,
	"extractor": "spectral_contrast",
	"aggregator": "diff_stats_1",
	"distance": "cosine_distance"
},
{
	"iicsr": 0.5340673284558177,
	"extractor": "spectral_contrast",
	"aggregator": "diff_stats_2",
	"distance": "manhattan_distance"
},
{
	"iicsr": 0.4010674830109545,
	"extractor": "spectral_contrast",
	"aggregator": "diff_stats_2",
	"distance": "euclidean_distance"
},
{
	"iicsr": 0.508285176551781,
	"extractor": "spectral_contrast",
	"aggregator": "diff_stats_2",
	"distance": "chebyshev_distance"
},
{
	"iicsr": 0.49128598838718984,
	"extractor": "spectral_contrast",
	"aggregator": "diff_stats_2",
	"distance": "cosine_distance"
},
{
	"iicsr": 0.6469148818736449,
	"extractor": "spectral_contrast",
	"aggregator": "statistical_summarization",
	"distance": "manhattan_distance"
},
{
	"iicsr": 0.5799302919899432,
	"extractor": "spectral_contrast",
	"aggregator": "statistical_summarization",
	"distance": "euclidean_distance"
},
{
	"iicsr": 0.620347524737676,
	"extractor": "spectral_contrast",
	"aggregator": "statistical_summarization",
	"distance": "chebyshev_distance"
},
{
	"iicsr": 0.4306312759961292,
	"extractor": "spectral_contrast",
	"aggregator": "statistical_summarization",
	"distance": "cosine_distance"
},
{
	"iicsr": 0.943811280272557,
	"extractor": "spectral_contrast",
	"aggregator": "gaussian_mixture_model_default",
	"distance": "manhattan_distance"
},
{
	"iicsr": 1.0352627268968817,
	"extractor": "spectral_contrast",
	"aggregator": "gaussian_mixture_model_default",
	"distance": "euclidean_distance"
},
{
	"iicsr": 1.093773939070211,
	"extractor": "spectral_contrast",
	"aggregator": "gaussian_mixture_model_default",
	"distance": "chebyshev_distance"
},
{
	"iicsr": 0.988270023603397,
	"extractor": "spectral_contrast",
	"aggregator": "gaussian_mixture_model_default",
	"distance": "cosine_distance"
},
{
	"iicsr": 0.033732287778259144,
	"extractor": "spectral_contrast",
	"aggregator": "vector_quantization",
	"distance": "manhattan_distance"
},
{
	"iicsr": 0.9295142686439527,
	"extractor": "spectral_contrast",
	"aggregator": "vector_quantization",
	"distance": "euclidean_distance"
},
{
	"iicsr": 0.9544930018073718,
	"extractor": "spectral_contrast",
	"aggregator": "vector_quantization",
	"distance": "chebyshev_distance"
},
{
	"iicsr": 0.006606842434011935,
	"extractor": "spectral_contrast",
	"aggregator": "vector_quantization",
	"distance": "cosine_distance"
},
{
	"iicsr": 0.021370138625414075,
	"extractor": "spectral_contrast",
	"aggregator": "vector_quantization_default",
	"distance": "manhattan_distance"
},
{
	"iicsr": 0.14801988710759542,
	"extractor": "spectral_contrast",
	"aggregator": "vector_quantization_default",
	"distance": "euclidean_distance"
},
{
	"iicsr": 0.020474543952235157,
	"extractor": "spectral_contrast",
	"aggregator": "vector_quantization_default",
	"distance": "chebyshev_distance"
},
{
	"iicsr": 0.006227042072423723,
	"extractor": "spectral_contrast",
	"aggregator": "vector_quantization_default",
	"distance": "cosine_distance"
},
{
	"iicsr": 0.9050306621595816,
	"extractor": "spectral_contrast",
	"aggregator": "statistical_summarization_2",
	"distance": "earth_movers_distance"
},
{
	"iicsr": 0.8662822951290444,
	"extractor": "spectral_contrast",
	"aggregator": "statistical_summarization_2",
	"distance": "monte_carlo_distance"
},
{
	"iicsr": 0.9949130408202025,
	"extractor": "tonnetz",
	"aggregator": "basic_stats_1",
	"distance": "manhattan_distance"
},
{
	"iicsr": 1.0241668814616467,
	"extractor": "tonnetz",
	"aggregator": "basic_stats_1",
	"distance": "euclidean_distance"
},
{
	"iicsr": 1.0127718405419903,
	"extractor": "tonnetz",
	"aggregator": "basic_stats_1",
	"distance": "chebyshev_distance"
},
{
	"iicsr": 1.0291451758895185,
	"extractor": "tonnetz",
	"aggregator": "basic_stats_1",
	"distance": "cosine_distance"
},
{
	"iicsr": 0.8555696873548218,
	"extractor": "tonnetz",
	"aggregator": "basic_stats_2",
	"distance": "manhattan_distance"
},
{
	"iicsr": 0.867234944075607,
	"extractor": "tonnetz",
	"aggregator": "basic_stats_2",
	"distance": "euclidean_distance"
},
{
	"iicsr": 0.9215114298404203,
	"extractor": "tonnetz",
	"aggregator": "basic_stats_2",
	"distance": "chebyshev_distance"
},
{
	"iicsr": 0.926896598465257,
	"extractor": "tonnetz",
	"aggregator": "basic_stats_2",
	"distance": "cosine_distance"
},
{
	"iicsr": 0.9857363183193244,
	"extractor": "tonnetz",
	"aggregator": "diff_stats_1",
	"distance": "manhattan_distance"
},
{
	"iicsr": 1.0242202782896372,
	"extractor": "tonnetz",
	"aggregator": "diff_stats_1",
	"distance": "euclidean_distance"
},
{
	"iicsr": 1.0152036112868712,
	"extractor": "tonnetz",
	"aggregator": "diff_stats_1",
	"distance": "chebyshev_distance"
},
{
	"iicsr": 1.0160341501838075,
	"extractor": "tonnetz",
	"aggregator": "diff_stats_1",
	"distance": "cosine_distance"
},
{
	"iicsr": 0.7545266074023734,
	"extractor": "tonnetz",
	"aggregator": "diff_stats_2",
	"distance": "manhattan_distance"
},
{
	"iicsr": 0.7452301318250146,
	"extractor": "tonnetz",
	"aggregator": "diff_stats_2",
	"distance": "euclidean_distance"
},
{
	"iicsr": 0.7910397690862463,
	"extractor": "tonnetz",
	"aggregator": "diff_stats_2",
	"distance": "chebyshev_distance"
},
{
	"iicsr": 0.8291671906940496,
	"extractor": "tonnetz",
	"aggregator": "diff_stats_2",
	"distance": "cosine_distance"
},
{
	"iicsr": 0.9714437466055663,
	"extractor": "tonnetz",
	"aggregator": "statistical_summarization",
	"distance": "manhattan_distance"
},
{
	"iicsr": 1.0057937343216703,
	"extractor": "tonnetz",
	"aggregator": "statistical_summarization",
	"distance": "euclidean_distance"
},
{
	"iicsr": 1.00235060909844,
	"extractor": "tonnetz",
	"aggregator": "statistical_summarization",
	"distance": "chebyshev_distance"
},
{
	"iicsr": 1.0945347339225355,
	"extractor": "tonnetz",
	"aggregator": "statistical_summarization",
	"distance": "cosine_distance"
},
{
	"iicsr": 0.8432245600252203,
	"extractor": "tonnetz",
	"aggregator": "gaussian_mixture_model_default",
	"distance": "manhattan_distance"
},
{
	"iicsr": 0.8692797239979172,
	"extractor": "tonnetz",
	"aggregator": "gaussian_mixture_model_default",
	"distance": "euclidean_distance"
},
{
	"iicsr": 1.00636270567981,
	"extractor": "tonnetz",
	"aggregator": "gaussian_mixture_model_default",
	"distance": "chebyshev_distance"
},
{
	"iicsr": 0.8237888188340791,
	"extractor": "tonnetz",
	"aggregator": "gaussian_mixture_model_default",
	"distance": "cosine_distance"
},
{
	"iicsr": 0.6487700481106882,
	"extractor": "tonnetz",
	"aggregator": "vector_quantization",
	"distance": "manhattan_distance"
},
{
	"iicsr": 0.9321964019175876,
	"extractor": "tonnetz",
	"aggregator": "vector_quantization",
	"distance": "euclidean_distance"
},
{
	"iicsr": 0.9526827122529713,
	"extractor": "tonnetz",
	"aggregator": "vector_quantization",
	"distance": "chebyshev_distance"
},
{
	"iicsr": 0.33239711590723675,
	"extractor": "tonnetz",
	"aggregator": "vector_quantization",
	"distance": "cosine_distance"
},
{
	"iicsr": 0.9856746936606208,
	"extractor": "tonnetz",
	"aggregator": "vector_quantization_default",
	"distance": "manhattan_distance"
},
{
	"iicsr": 0.9748347556791945,
	"extractor": "tonnetz",
	"aggregator": "vector_quantization_default",
	"distance": "euclidean_distance"
},
{
	"iicsr": 0.9486452517742026,
	"extractor": "tonnetz",
	"aggregator": "vector_quantization_default",
	"distance": "chebyshev_distance"
},
{
	"iicsr": 1.0023279799384681,
	"extractor": "tonnetz",
	"aggregator": "vector_quantization_default",
	"distance": "cosine_distance"
},
{
	"iicsr": 1.059954492940486,
	"extractor": "tonnetz",
	"aggregator": "statistical_summarization_2",
	"distance": "earth_movers_distance"
},
{
	"iicsr": 0.9777988478626519,
	"extractor": "tonnetz",
	"aggregator": "statistical_summarization_2",
	"distance": "monte_carlo_distance"
},
{
	"iicsr": 0.995706794796595,
	"extractor": "chroma_stft",
	"aggregator": "basic_stats_1",
	"distance": "manhattan_distance_dot_product_circular_shifts"
},
{
	"iicsr": 1.000775982193778,
	"extractor": "chroma_stft",
	"aggregator": "basic_stats_1",
	"distance": "euclidean_distance_dot_product_circular_shifts"
},
{
	"iicsr": 1.0278702498588526,
	"extractor": "chroma_stft",
	"aggregator": "basic_stats_1",
	"distance": "chebyshev_distance_dot_product_circular_shifts"
},
{
	"iicsr": 1.017806804702783,
	"extractor": "chroma_stft",
	"aggregator": "basic_stats_1",
	"distance": "cosine_distance_dot_product_circular_shifts"
},
{
	"iicsr": 0.997402569314646,
	"extractor": "chroma_stft",
	"aggregator": "basic_stats_2",
	"distance": "manhattan_distance_dot_product_circular_shifts"
},
{
	"iicsr": 1.0020943079346483,
	"extractor": "chroma_stft",
	"aggregator": "basic_stats_2",
	"distance": "euclidean_distance_dot_product_circular_shifts"
},
{
	"iicsr": 1.0299405974894005,
	"extractor": "chroma_stft",
	"aggregator": "basic_stats_2",
	"distance": "chebyshev_distance_dot_product_circular_shifts"
},
{
	"iicsr": 1.0075755937627737,
	"extractor": "chroma_stft",
	"aggregator": "basic_stats_2",
	"distance": "cosine_distance_dot_product_circular_shifts"
},
{
	"iicsr": 0.9109219713608412,
	"extractor": "chroma_stft",
	"aggregator": "diff_stats_1",
	"distance": "manhattan_distance_dot_product_circular_shifts"
},
{
	"iicsr": 0.9572329641808407,
	"extractor": "chroma_stft",
	"aggregator": "diff_stats_1",
	"distance": "euclidean_distance_dot_product_circular_shifts"
},
{
	"iicsr": 1.0285011402053128,
	"extractor": "chroma_stft",
	"aggregator": "diff_stats_1",
	"distance": "chebyshev_distance_dot_product_circular_shifts"
},
{
	"iicsr": 0.9800212730766628,
	"extractor": "chroma_stft",
	"aggregator": "diff_stats_1",
	"distance": "cosine_distance_dot_product_circular_shifts"
},
{
	"iicsr": 1.0113006987449928,
	"extractor": "chroma_stft",
	"aggregator": "diff_stats_2",
	"distance": "manhattan_distance_dot_product_circular_shifts"
},
{
	"iicsr": 1.0318779198033328,
	"extractor": "chroma_stft",
	"aggregator": "diff_stats_2",
	"distance": "euclidean_distance_dot_product_circular_shifts"
},
{
	"iicsr": 0.9404537703925937,
	"extractor": "chroma_stft",
	"aggregator": "diff_stats_2",
	"distance": "chebyshev_distance_dot_product_circular_shifts"
},
{
	"iicsr": 1.0109295829727056,
	"extractor": "chroma_stft",
	"aggregator": "diff_stats_2",
	"distance": "cosine_distance_dot_product_circular_shifts"
},
{
	"iicsr": 0.882727264532545,
	"extractor": "chroma_stft",
	"aggregator": "statistical_summarization",
	"distance": "manhattan_distance_dot_product_circular_shifts"
},
{
	"iicsr": 0.9087079482264113,
	"extractor": "chroma_stft",
	"aggregator": "statistical_summarization",
	"distance": "euclidean_distance_dot_product_circular_shifts"
},
{
	"iicsr": 1.0314547577319095,
	"extractor": "chroma_stft",
	"aggregator": "statistical_summarization",
	"distance": "chebyshev_distance_dot_product_circular_shifts"
},
{
	"iicsr": 0.940225845483317,
	"extractor": "chroma_stft",
	"aggregator": "statistical_summarization",
	"distance": "cosine_distance_dot_product_circular_shifts"
},
{
	"iicsr": 0.8313134056056116,
	"extractor": "chroma_cqt",
	"aggregator": "basic_stats_1",
	"distance": "manhattan_distance_dot_product_circular_shifts"
},
{
	"iicsr": 0.7341125317582492,
	"extractor": "chroma_cqt",
	"aggregator": "basic_stats_1",
	"distance": "euclidean_distance_dot_product_circular_shifts"
},
{
	"iicsr": 0.5775540401271142,
	"extractor": "chroma_cqt",
	"aggregator": "basic_stats_1",
	"distance": "chebyshev_distance_dot_product_circular_shifts"
},
{
	"iicsr": 0.854397710134943,
	"extractor": "chroma_cqt",
	"aggregator": "basic_stats_1",
	"distance": "cosine_distance_dot_product_circular_shifts"
},
{
	"iicsr": 0.8294783434246501,
	"extractor": "chroma_cqt",
	"aggregator": "basic_stats_2",
	"distance": "manhattan_distance_dot_product_circular_shifts"
},
{
	"iicsr": 0.7361091407671452,
	"extractor": "chroma_cqt",
	"aggregator": "basic_stats_2",
	"distance": "euclidean_distance_dot_product_circular_shifts"
},
{
	"iicsr": 0.5775685060496613,
	"extractor": "chroma_cqt",
	"aggregator": "basic_stats_2",
	"distance": "chebyshev_distance_dot_product_circular_shifts"
},
{
	"iicsr": 0.8169718760950608,
	"extractor": "chroma_cqt",
	"aggregator": "basic_stats_2",
	"distance": "cosine_distance_dot_product_circular_shifts"
},
{
	"iicsr": 0.7977177509296306,
	"extractor": "chroma_cqt",
	"aggregator": "diff_stats_1",
	"distance": "manhattan_distance_dot_product_circular_shifts"
},
{
	"iicsr": 0.7318958181305689,
	"extractor": "chroma_cqt",
	"aggregator": "diff_stats_1",
	"distance": "euclidean_distance_dot_product_circular_shifts"
},
{
	"iicsr": 0.5775540401271142,
	"extractor": "chroma_cqt",
	"aggregator": "diff_stats_1",
	"distance": "chebyshev_distance_dot_product_circular_shifts"
},
{
	"iicsr": 0.856983361795362,
	"extractor": "chroma_cqt",
	"aggregator": "diff_stats_1",
	"distance": "cosine_distance_dot_product_circular_shifts"
},
{
	"iicsr": 0.9210508775629636,
	"extractor": "chroma_cqt",
	"aggregator": "diff_stats_2",
	"distance": "manhattan_distance_dot_product_circular_shifts"
},
{
	"iicsr": 0.88756786765059,
	"extractor": "chroma_cqt",
	"aggregator": "diff_stats_2",
	"distance": "euclidean_distance_dot_product_circular_shifts"
},
{
	"iicsr": 0.4803857999987556,
	"extractor": "chroma_cqt",
	"aggregator": "diff_stats_2",
	"distance": "chebyshev_distance_dot_product_circular_shifts"
},
{
	"iicsr": 0.9002600061647725,
	"extractor": "chroma_cqt",
	"aggregator": "diff_stats_2",
	"distance": "cosine_distance_dot_product_circular_shifts"
},
{
	"iicsr": 0.8136921118102285,
	"extractor": "chroma_cqt",
	"aggregator": "statistical_summarization",
	"distance": "manhattan_distance_dot_product_circular_shifts"
},
{
	"iicsr": 0.7378604497830735,
	"extractor": "chroma_cqt",
	"aggregator": "statistical_summarization",
	"distance": "euclidean_distance_dot_product_circular_shifts"
},
{
	"iicsr": 0.5751437774769883,
	"extractor": "chroma_cqt",
	"aggregator": "statistical_summarization",
	"distance": "chebyshev_distance_dot_product_circular_shifts"
},
{
	"iicsr": 0.8997930564529698,
	"extractor": "chroma_cqt",
	"aggregator": "statistical_summarization",
	"distance": "cosine_distance_dot_product_circular_shifts"
},
{
	"iicsr": 0.792426355691453,
	"extractor": "chroma_cens",
	"aggregator": "basic_stats_1",
	"distance": "manhattan_distance_dot_product_circular_shifts"
},
{
	"iicsr": 0.8104109865599008,
	"extractor": "chroma_cens",
	"aggregator": "basic_stats_1",
	"distance": "euclidean_distance_dot_product_circular_shifts"
},
{
	"iicsr": 0.7855860273795011,
	"extractor": "chroma_cens",
	"aggregator": "basic_stats_1",
	"distance": "chebyshev_distance_dot_product_circular_shifts"
},
{
	"iicsr": 0.8841873793963123,
	"extractor": "chroma_cens",
	"aggregator": "basic_stats_1",
	"distance": "cosine_distance_dot_product_circular_shifts"
},
{
	"iicsr": 0.7946094465322218,
	"extractor": "chroma_cens",
	"aggregator": "basic_stats_2",
	"distance": "manhattan_distance_dot_product_circular_shifts"
},
{
	"iicsr": 0.7970382649083579,
	"extractor": "chroma_cens",
	"aggregator": "basic_stats_2",
	"distance": "euclidean_distance_dot_product_circular_shifts"
},
{
	"iicsr": 0.7940529243754275,
	"extractor": "chroma_cens",
	"aggregator": "basic_stats_2",
	"distance": "chebyshev_distance_dot_product_circular_shifts"
},
{
	"iicsr": 0.9253232462401211,
	"extractor": "chroma_cens",
	"aggregator": "basic_stats_2",
	"distance": "cosine_distance_dot_product_circular_shifts"
},
{
	"iicsr": 0.7926072797745876,
	"extractor": "chroma_cens",
	"aggregator": "diff_stats_1",
	"distance": "manhattan_distance_dot_product_circular_shifts"
},
{
	"iicsr": 0.8105913384545076,
	"extractor": "chroma_cens",
	"aggregator": "diff_stats_1",
	"distance": "euclidean_distance_dot_product_circular_shifts"
},
{
	"iicsr": 0.7855860273795011,
	"extractor": "chroma_cens",
	"aggregator": "diff_stats_1",
	"distance": "chebyshev_distance_dot_product_circular_shifts"
},
{
	"iicsr": 0.8842610924163092,
	"extractor": "chroma_cens",
	"aggregator": "diff_stats_1",
	"distance": "cosine_distance_dot_product_circular_shifts"
},
{
	"iicsr": 0.6555064501740128,
	"extractor": "chroma_cens",
	"aggregator": "diff_stats_2",
	"distance": "manhattan_distance_dot_product_circular_shifts"
},
{
	"iicsr": 0.5816248528383359,
	"extractor": "chroma_cens",
	"aggregator": "diff_stats_2",
	"distance": "euclidean_distance_dot_product_circular_shifts"
},
{
	"iicsr": 0.47092231495831793,
	"extractor": "chroma_cens",
	"aggregator": "diff_stats_2",
	"distance": "chebyshev_distance_dot_product_circular_shifts"
},
{
	"iicsr": 0.6878903217145689,
	"extractor": "chroma_cens",
	"aggregator": "diff_stats_2",
	"distance": "cosine_distance_dot_product_circular_shifts"
},
{
	"iicsr": 0.7766642816221807,
	"extractor": "chroma_cens",
	"aggregator": "statistical_summarization",
	"distance": "manhattan_distance_dot_product_circular_shifts"
},
{
	"iicsr": 0.8675513718815067,
	"extractor": "chroma_cens",
	"aggregator": "statistical_summarization",
	"distance": "euclidean_distance_dot_product_circular_shifts"
},
{
	"iicsr": 0.7819701126628721,
	"extractor": "chroma_cens",
	"aggregator": "statistical_summarization",
	"distance": "chebyshev_distance_dot_product_circular_shifts"
},
{
	"iicsr": 0.9355337046634895,
	"extractor": "chroma_cens",
	"aggregator": "statistical_summarization",
	"distance": "cosine_distance_dot_product_circular_shifts"
},
{
	"iicsr": 1.0167838664034925,
	"extractor": "beat_synchronous_chroma_stft",
	"aggregator": "basic_stats_1",
	"distance": "manhattan_distance_dot_product_circular_shifts"
},
{
	"iicsr": 1.0220919616190898,
	"extractor": "beat_synchronous_chroma_stft",
	"aggregator": "basic_stats_1",
	"distance": "euclidean_distance_dot_product_circular_shifts"
},
{
	"iicsr": 0.9776129438214094,
	"extractor": "beat_synchronous_chroma_stft",
	"aggregator": "basic_stats_1",
	"distance": "chebyshev_distance_dot_product_circular_shifts"
},
{
	"iicsr": 1.0396703402391934,
	"extractor": "beat_synchronous_chroma_stft",
	"aggregator": "basic_stats_1",
	"distance": "cosine_distance_dot_product_circular_shifts"
},
{
	"iicsr": 1.0271580336418138,
	"extractor": "beat_synchronous_chroma_stft",
	"aggregator": "basic_stats_2",
	"distance": "manhattan_distance_dot_product_circular_shifts"
},
{
	"iicsr": 1.0164128674502961,
	"extractor": "beat_synchronous_chroma_stft",
	"aggregator": "basic_stats_2",
	"distance": "euclidean_distance_dot_product_circular_shifts"
},
{
	"iicsr": 0.9405281251066371,
	"extractor": "beat_synchronous_chroma_stft",
	"aggregator": "basic_stats_2",
	"distance": "chebyshev_distance_dot_product_circular_shifts"
},
{
	"iicsr": 1.0310015285313932,
	"extractor": "beat_synchronous_chroma_stft",
	"aggregator": "basic_stats_2",
	"distance": "cosine_distance_dot_product_circular_shifts"
},
{
	"iicsr": 1.0191685030676476,
	"extractor": "beat_synchronous_chroma_stft",
	"aggregator": "diff_stats_1",
	"distance": "manhattan_distance_dot_product_circular_shifts"
},
{
	"iicsr": 1.025097701423578,
	"extractor": "beat_synchronous_chroma_stft",
	"aggregator": "diff_stats_1",
	"distance": "euclidean_distance_dot_product_circular_shifts"
},
{
	"iicsr": 0.9820184237103716,
	"extractor": "beat_synchronous_chroma_stft",
	"aggregator": "diff_stats_1",
	"distance": "chebyshev_distance_dot_product_circular_shifts"
},
{
	"iicsr": 1.0268152208982868,
	"extractor": "beat_synchronous_chroma_stft",
	"aggregator": "diff_stats_1",
	"distance": "cosine_distance_dot_product_circular_shifts"
},
{
	"iicsr": 0.9354485765705784,
	"extractor": "beat_synchronous_chroma_stft",
	"aggregator": "diff_stats_2",
	"distance": "manhattan_distance_dot_product_circular_shifts"
},
{
	"iicsr": 0.8607597014305435,
	"extractor": "beat_synchronous_chroma_stft",
	"aggregator": "diff_stats_2",
	"distance": "euclidean_distance_dot_product_circular_shifts"
},
{
	"iicsr": 0.7120423132349752,
	"extractor": "beat_synchronous_chroma_stft",
	"aggregator": "diff_stats_2",
	"distance": "chebyshev_distance_dot_product_circular_shifts"
},
{
	"iicsr": 0.9922198562150807,
	"extractor": "beat_synchronous_chroma_stft",
	"aggregator": "diff_stats_2",
	"distance": "cosine_distance_dot_product_circular_shifts"
},
{
	"iicsr": 0.9750182588113168,
	"extractor": "beat_synchronous_chroma_stft",
	"aggregator": "statistical_summarization",
	"distance": "manhattan_distance_dot_product_circular_shifts"
},
{
	"iicsr": 1.0062044431434096,
	"extractor": "beat_synchronous_chroma_stft",
	"aggregator": "statistical_summarization",
	"distance": "euclidean_distance_dot_product_circular_shifts"
},
{
	"iicsr": 1.1168118010997377,
	"extractor": "beat_synchronous_chroma_stft",
	"aggregator": "statistical_summarization",
	"distance": "chebyshev_distance_dot_product_circular_shifts"
},
{
	"iicsr": 1.0176917530518124,
	"extractor": "beat_synchronous_chroma_stft",
	"aggregator": "statistical_summarization",
	"distance": "cosine_distance_dot_product_circular_shifts"
},
{
	"iicsr": 0.8313254137351815,
	"extractor": "beat_synchronous_chroma_cqt",
	"aggregator": "basic_stats_1",
	"distance": "manhattan_distance_dot_product_circular_shifts"
},
{
	"iicsr": 0.7821148867754604,
	"extractor": "beat_synchronous_chroma_cqt",
	"aggregator": "basic_stats_1",
	"distance": "euclidean_distance_dot_product_circular_shifts"
},
{
	"iicsr": 0.7236077158394436,
	"extractor": "beat_synchronous_chroma_cqt",
	"aggregator": "basic_stats_1",
	"distance": "chebyshev_distance_dot_product_circular_shifts"
},
{
	"iicsr": 0.9051002797444125,
	"extractor": "beat_synchronous_chroma_cqt",
	"aggregator": "basic_stats_1",
	"distance": "cosine_distance_dot_product_circular_shifts"
},
{
	"iicsr": 0.8126587206036151,
	"extractor": "beat_synchronous_chroma_cqt",
	"aggregator": "basic_stats_2",
	"distance": "manhattan_distance_dot_product_circular_shifts"
},
{
	"iicsr": 0.8020717664866407,
	"extractor": "beat_synchronous_chroma_cqt",
	"aggregator": "basic_stats_2",
	"distance": "euclidean_distance_dot_product_circular_shifts"
},
{
	"iicsr": 0.8594473966125504,
	"extractor": "beat_synchronous_chroma_cqt",
	"aggregator": "basic_stats_2",
	"distance": "chebyshev_distance_dot_product_circular_shifts"
},
{
	"iicsr": 0.9175754187209088,
	"extractor": "beat_synchronous_chroma_cqt",
	"aggregator": "basic_stats_2",
	"distance": "cosine_distance_dot_product_circular_shifts"
},
{
	"iicsr": 0.8623644155276015,
	"extractor": "beat_synchronous_chroma_cqt",
	"aggregator": "diff_stats_1",
	"distance": "manhattan_distance_dot_product_circular_shifts"
},
{
	"iicsr": 0.8067665090357302,
	"extractor": "beat_synchronous_chroma_cqt",
	"aggregator": "diff_stats_1",
	"distance": "euclidean_distance_dot_product_circular_shifts"
},
{
	"iicsr": 0.7265896131337901,
	"extractor": "beat_synchronous_chroma_cqt",
	"aggregator": "diff_stats_1",
	"distance": "chebyshev_distance_dot_product_circular_shifts"
},
{
	"iicsr": 0.8990389930444852,
	"extractor": "beat_synchronous_chroma_cqt",
	"aggregator": "diff_stats_1",
	"distance": "cosine_distance_dot_product_circular_shifts"
},
{
	"iicsr": 0.6936743584406575,
	"extractor": "beat_synchronous_chroma_cqt",
	"aggregator": "diff_stats_2",
	"distance": "manhattan_distance_dot_product_circular_shifts"
},
{
	"iicsr": 0.6243911215086275,
	"extractor": "beat_synchronous_chroma_cqt",
	"aggregator": "diff_stats_2",
	"distance": "euclidean_distance_dot_product_circular_shifts"
},
{
	"iicsr": 0.6228887676111534,
	"extractor": "beat_synchronous_chroma_cqt",
	"aggregator": "diff_stats_2",
	"distance": "chebyshev_distance_dot_product_circular_shifts"
},
{
	"iicsr": 0.7623038452662292,
	"extractor": "beat_synchronous_chroma_cqt",
	"aggregator": "diff_stats_2",
	"distance": "cosine_distance_dot_product_circular_shifts"
},
{
	"iicsr": 0.7858766442738838,
	"extractor": "beat_synchronous_chroma_cqt",
	"aggregator": "statistical_summarization",
	"distance": "manhattan_distance_dot_product_circular_shifts"
},
{
	"iicsr": 0.7759976485724032,
	"extractor": "beat_synchronous_chroma_cqt",
	"aggregator": "statistical_summarization",
	"distance": "euclidean_distance_dot_product_circular_shifts"
},
{
	"iicsr": 0.7198337173407247,
	"extractor": "beat_synchronous_chroma_cqt",
	"aggregator": "statistical_summarization",
	"distance": "chebyshev_distance_dot_product_circular_shifts"
},
{
	"iicsr": 0.9433605689886838,
	"extractor": "beat_synchronous_chroma_cqt",
	"aggregator": "statistical_summarization",
	"distance": "cosine_distance_dot_product_circular_shifts"
},
{
	"iicsr": 0.8381008994065215,
	"extractor": "beat_synchronous_chroma_cens",
	"aggregator": "basic_stats_1",
	"distance": "manhattan_distance_dot_product_circular_shifts"
},
{
	"iicsr": 0.8263537602454297,
	"extractor": "beat_synchronous_chroma_cens",
	"aggregator": "basic_stats_1",
	"distance": "euclidean_distance_dot_product_circular_shifts"
},
{
	"iicsr": 0.8139687882062777,
	"extractor": "beat_synchronous_chroma_cens",
	"aggregator": "basic_stats_1",
	"distance": "chebyshev_distance_dot_product_circular_shifts"
},
{
	"iicsr": 0.9004730928037477,
	"extractor": "beat_synchronous_chroma_cens",
	"aggregator": "basic_stats_1",
	"distance": "cosine_distance_dot_product_circular_shifts"
},
{
	"iicsr": 0.8965812075287473,
	"extractor": "beat_synchronous_chroma_cens",
	"aggregator": "basic_stats_2",
	"distance": "manhattan_distance_dot_product_circular_shifts"
},
{
	"iicsr": 0.8527286224669871,
	"extractor": "beat_synchronous_chroma_cens",
	"aggregator": "basic_stats_2",
	"distance": "euclidean_distance_dot_product_circular_shifts"
},
{
	"iicsr": 0.7313827788720343,
	"extractor": "beat_synchronous_chroma_cens",
	"aggregator": "basic_stats_2",
	"distance": "chebyshev_distance_dot_product_circular_shifts"
},
{
	"iicsr": 0.9715858420783735,
	"extractor": "beat_synchronous_chroma_cens",
	"aggregator": "basic_stats_2",
	"distance": "cosine_distance_dot_product_circular_shifts"
},
{
	"iicsr": 0.8911037324976565,
	"extractor": "beat_synchronous_chroma_cens",
	"aggregator": "diff_stats_1",
	"distance": "manhattan_distance_dot_product_circular_shifts"
},
{
	"iicsr": 0.8406208565497068,
	"extractor": "beat_synchronous_chroma_cens",
	"aggregator": "diff_stats_1",
	"distance": "euclidean_distance_dot_product_circular_shifts"
},
{
	"iicsr": 0.8169558146696972,
	"extractor": "beat_synchronous_chroma_cens",
	"aggregator": "diff_stats_1",
	"distance": "chebyshev_distance_dot_product_circular_shifts"
},
{
	"iicsr": 0.9050942721848731,
	"extractor": "beat_synchronous_chroma_cens",
	"aggregator": "diff_stats_1",
	"distance": "cosine_distance_dot_product_circular_shifts"
},
{
	"iicsr": 0.7922103229748626,
	"extractor": "beat_synchronous_chroma_cens",
	"aggregator": "diff_stats_2",
	"distance": "manhattan_distance_dot_product_circular_shifts"
},
{
	"iicsr": 0.6973237170419441,
	"extractor": "beat_synchronous_chroma_cens",
	"aggregator": "diff_stats_2",
	"distance": "euclidean_distance_dot_product_circular_shifts"
},
{
	"iicsr": 0.787243184023778,
	"extractor": "beat_synchronous_chroma_cens",
	"aggregator": "diff_stats_2",
	"distance": "chebyshev_distance_dot_product_circular_shifts"
},
{
	"iicsr": 0.928230305636332,
	"extractor": "beat_synchronous_chroma_cens",
	"aggregator": "diff_stats_2",
	"distance": "cosine_distance_dot_product_circular_shifts"
},
{
	"iicsr": 0.8579016820321085,
	"extractor": "beat_synchronous_chroma_cens",
	"aggregator": "statistical_summarization",
	"distance": "manhattan_distance_dot_product_circular_shifts"
},
{
	"iicsr": 0.852320385002156,
	"extractor": "beat_synchronous_chroma_cens",
	"aggregator": "statistical_summarization",
	"distance": "euclidean_distance_dot_product_circular_shifts"
},
{
	"iicsr": 0.8099339247481476,
	"extractor": "beat_synchronous_chroma_cens",
	"aggregator": "statistical_summarization",
	"distance": "chebyshev_distance_dot_product_circular_shifts"
},
{
	"iicsr": 0.9184024012929778,
	"extractor": "beat_synchronous_chroma_cens",
	"aggregator": "statistical_summarization",
	"distance": "cosine_distance_dot_product_circular_shifts"
}
]}